{
"meta":{"test_sets":[],"test_metrics":[],"learn_metrics":[{"best_value":"Min","name":"RMSE"}],"launch_mode":"Train","parameters":"","iteration_count":1000,"learn_sets":["learn"],"name":"experiment"},
"iterations":[
{"learn":[0.9636585417],"iteration":0,"passed_time":0.01820328663,"remaining_time":18.18508334,,
{"learn":[0.9482569311],"iteration":1,"passed_time":0.03106422321,"remaining_time":15.50104738,
{"learn":[0.9517785692],"iteration":2,"passed_time":0.05332953798,"remaining_time":17.72318312},
{"learn":[0.9390042013],"iteration":3,"passed_time":0.0813211712,"remaining_time":20.24897163},
{"learn":[0.927837418],"iteration":4,"passed_time":0.09787969035,"remaining_time":19.47805838},
{"learn":[0.9168700165],"iteration":5,"passed_time":0.1241596857,"remaining_time":20.56912126},
{"learn":[0.9058646799],"iteration":6,"passed_time":0.1451957216,"remaining_time":20.59705022,
{"learn":[0.8754001897],"iteration":7,"passed_time":0.1785207083,"remaining_time":22.13656783},
{"learn":[0.8634868704],"iteration":8,"passed_time":0.207409324,"remaining_time":22.83807112},
{"learn":[0.8547304277],"iteration":9,"passed_time":0.2285412416,"remaining_time":22.62558291},
{"learn":[0.8455135085],"iteration":10,"passed_time":0.2473667318,"remaining_time":22.24051798},
{"learn":[0.8365356782],"iteration":11,"passed_time":0.2618593735,"remaining_time":21.55975509},
{"learn":[0.8279113407],"iteration":12,"passed_time":0.2814540903,"remaining_time":21.36886055},
{"learn":[0.8192564931],"iteration":13,"passed_time":0.2926315132,"remaining_time":20.60961943},
{"learn":[0.8129353937],"iteration":14,"passed_time":0.3084497713,"remaining_time":20.25486832},
{"learn":[0.8047412276],"iteration":15,"passed_time":0.3211691764,"remaining_time":19.75190435},
,
{"learn":[0.8125467781],"iteration":16,"passed_time":0.3363488026,"remaining_time":19.448874,
{"learn":[0.7902615651],"iteration":17,"passed_time":0.3495556287,"remaining_time":19.07020152},
{"learn":[0.7827861922],"iteration":18,"passed_time":0.3611335913,"remaining_time":18.64589753},
{"learn":[0.7772655071],"iteration":19,"passed_time":0.3794705823,"remaining_time":18.59405853},
{"learn":[0.7712860696],"iteration":20,"passed_time":0.3926150341,"remaining_time":18.30333897},
{"learn":[0.766302486],"iteration":21,"passed_time":0.4076841391,"remaining_time":18.12341309},
{"learn":[0.7598030283],"iteration":22,"passed_time":0.4204858511,"remaining_time":17.86150768},
{"learn":[0.7529054108],"iteration":23,"passed_time":0.4369780169,"remaining_time":17.77043936},
{"learn":[0.7476028032],"iteration":24,"passed_time":0.448895727,"remaining_time":17.50693335},
{"l,
{"learn":[0.7575122654],"iteration":25,"passed_time":0.4728077022,"remaining_time":17.7121,
{"l,
{"learn":[0.7519501571],"iteration":26,"passed_time":0.4904379682,"remaining_time":17.6739,
{"l,
{"learn":[0.7476601322],"iteration":27,"passed_time":0.5092861155,"remaining_time":17.6795,
{"l,
{"learn":[0.7414109922],"iteration":28,"passed_time":0.5374836681,"remaining_time":17.9964,
{"learn":[0.7206381052],"iteration":29,"passed_time":0.5574341808,"remaining_time":18.02370518},
{"learn":[0.7151545912],"iteration":30,"passed_time":0.5798042708,"remaining_time":18.1235593},
{"learn":[0.7098932496],"iteration":31,"passed_time":0.5915003747,"remaining_time":17.89288634},
{"learn":[0.7038610512],"iteration":32,"passed_time":0.6137438875,"remaining_time":17.98455573},
{"learn":[0.7001876204],"iteration":33,"passed_time":0.6250097644,"remaining_time":17.75763036},
{"learn":[0.696368728],"iteration":34,"passed_time":0.6418688147,"remaining_time":17.69724018},
{"learn":[0.6927925179],"iteration":35,"passed_time":0.6543904939,"remaining_time":17.52312323},
{"learn":[0.6886862334],"iteration":36,"passed_time":0.6728184902,"remaining_time":17.51146503},
{"learn":[0.6845198352],"iteration":37,"passed_time":0.688524914,"remaining_time":17.43055177},
{"learn":[0.680057015],"iteration":38,"passed_time":0.7081120949,"remaining_time":17.44860829},
{"learn":[0.6759785894],"iteration":39,"passed_time":0.7192937102,"remaining_time":17.26304905},
{"learn":[0.6714129253],"iteration":40,"passed_time":0.7354072009,"remaining_time":17.2013538},
{"lear,
{"learn":[0.6837865878],"iteration":41,"passed_time":0.7461686492,"remaining_time":17.0,
{"lear,
{"learn":[0.678077966],"iteration":42,"passed_time":0.7760363195,"remaining_time":17.27,
{"lea,
{"learn":[0.6740814903],"iteration":43,"passed_time":0.7878184648,"remaining_time":17.1,
{"lear,
{"learn":[0.670109435],"iteration":44,"passed_time":0.8151968215,"remaining_time":17.3,
{"lea,
{"learn":[0.6648467972],"iteration":45,"passed_time":0.8347706036,"remaining_time":17.31,
{"lea,
{"learn":[0.6613446942],"iteration":46,"passed_time":0.8704025322,"remaining_time":17.6,
{"lear,
{"learn":[0.6584734739],"iteration":47,"passed_time":0.8872137245,"remaining_time":17.,
{"learn,
{"learn":[0.6557314215],"iteration":48,"passed_time":0.9135382947,"remaining_time":17,
{"learn",
{"learn":[0.6523200278],"iteration":49,"passed_time":0.9406648671,"remaining_time":17,
{"learn",
{"learn":[0.6489272345],"iteration":50,"passed_time":0.9718297097,"remaining_time":1,
{"learn":,
{"learn":[0.6462562588],"iteration":51,"passed_time":0.9897269624,"remaining_time":1,
{"learn":,
{"learn":[0.6430356739],"iteration":52,"passed_time":1.017293224,"remaining_time":1,
{"learn":,
{"learn":[0.6391169089],"iteration":53,"passed_time":1.039601855,"remaining_time":1,
{"learn":,
{"learn":[0.6363813083],"iteration":54,"passed_time":1.081421333,"remaining_time":,
{"learn":[,
{"learn":[0.6340292386],"iteration":55,"passed_time":1.103628773,"remaining_time",
{"learn":[0,
{"learn":[0.6309414195],"iteration":56,"passed_time":1.129376405,"remaining_time",
{"learn":[0,
{"learn":[0.6287633895],"iteration":57,"passed_time":1.150400996,"remaining_time",
{"learn":[0,
{"learn":[0.6249858472],"iteration":58,"passed_time":1.180983015,"remaining_time",
{"learn":[0,
{"learn":[0.622076927],"iteration":59,"passed_time":1.205002976,"remaining_time":,
{"learn":[,
{"learn":[0.6192553718],"iteration":60,"passed_time":1.230226099,"remaining_time":,
{"learn":[,
{"learn":[0.6161770798],"iteration":61,"passed_time":1.247062561,"remaining_time,
{"learn":[0.,
{"learn":[0.6139369661],"iteration":62,"passed_time":1.286215768,"remaining_time,
{"learn":[0.,
{"learn":[0.6115099428],"iteration":63,"passed_time":1.534269996,"remaining_time,
{"learn":[0,
{"learn":[0.6092406663],"iteration":64,"passed_time":1.569011621,"remaining_time",
{"learn":[,
{"learn":[0.607086481],"iteration":65,"passed_time":1.580847327,"remaining_time":2,
{"learn":,
{"learn":[0.6046540119],"iteration":66,"passed_time":1.595638054,"remaining_time":,
{"learn":[,
{"learn":[0.6022505527],"iteration":67,"passed_time":1.609436171,"remaining_time":,
{"learn":[,
{"learn":[0.5999381202],"iteration":68,"passed_time":1.624365021,"remaining_time":,
{"learn":[,
{"learn":[0.5961809042],"iteration":69,"passed_time":1.636996592,"remaining_time":,
{"learn":[,
{"learn":[0.5934224194],"iteration":70,"passed_time":1.655178547,"remaining_time":,
{"learn":[,
{"learn":[0.5911114993],"iteration":71,"passed_time":1.669155481,"remaining_time":,
{"learn":[,
{"learn":[0.5890106668],"iteration":72,"passed_time":1.680814559,"remaining_time":,
{"learn":[,
{"learn":[0.5879402013],"iteration":73,"passed_time":1.697184729,"remaining_time",
{"learn":[0,
{"learn":[0.5863680036],"iteration":74,"passed_time":1.70803377,"remaining_time",
{"learn":[0,
{"learn":[0.5846637983],"iteration":75,"passed_time":1.722390611,"remaining_tim,
{"learn":[0.5,
{"learn":[0.5828547857],"iteration":76,"passed_time":1.743972411,"remaining_tim,
{"learn":[0.5,
{"learn":[0.5803425748],"iteration":77,"passed_time":1.76455407,"remaining_time,
{"learn":[0.,
{"learn":[0.578243964],"iteration":78,"passed_time":1.788628429,"remaining_time,
{"learn":[0.,
{"learn":[0.5764193328],"iteration":79,"passed_time":1.80504576,"remaining_time",
{"learn":[0,
{"learn":[0.5747947823],"iteration":80,"passed_time":1.827127805,"remaining_time",
{"learn":[0,
{"learn":[0.5728955521],"iteration":81,"passed_time":1.843572982,"remaining_time",
{"learn":[0,
{"learn":[0.5712863325],"iteration":82,"passed_time":1.864272469,"remaining_time,
{"learn":[0.,
{"learn":[0.5682664833],"iteration":83,"passed_time":1.876030891,"remaining_tim,
{"learn":[0.,
{"learn":[0.5669981835],"iteration":84,"passed_time":1.891061863,"remaining_tim,
{"learn":[0.5,
{"learn":[0.5651121725],"iteration":85,"passed_time":1.903948411,"remaining_tim,
{"learn":[0.,
{"learn":[0.5633924782],"iteration":86,"passed_time":1.918490538,"remaining_tim,
{"learn":[0.5,
{"learn":[0.5618539965],"iteration":87,"passed_time":1.92931748,"remaining_tim,
{"learn":[0.5,
{"learn":[0.5605164839],"iteration":88,"passed_time":1.946307641,"remaining_tim,
{"learn":[0.5,
{"learn":[0.5588287037],"iteration":89,"passed_time":1.965068445,"remaining_tim,
{"learn":[0.5,
{"learn":[0.5568685208],"iteration":90,"passed_time":1.978137787,"remaining_ti,
{"learn":[0.54,
{"learn":[0.555229957],"iteration":91,"passed_time":1.994694061,"remaining_tim,
{"learn":[0.5,
{"learn":[0.5540503564],"iteration":92,"passed_time":2.006235839,"remaining_tim,
{"learn":[0.5,
{"learn":[0.5522188062],"iteration":93,"passed_time":2.067968204,"remaining_tim,
{"learn":[0.5,
{"learn":[0.549582622],"iteration":94,"passed_time":2.134300038,"remaining_time,
{"learn":[0.,
{"learn":[0.5479319673],"iteration":95,"passed_time":2.195780503,"remaining_tim,
{"learn":[0.5,
{"learn":[0.5463905937],"iteration":96,"passed_time":2.219709187,"remaining_tim,
{"learn":[0.5,
{"learn":[0.5445325809],"iteration":97,"passed_time":2.259487916,"remaining_tim,
{"learn":[0.5,
{"learn":[0.5420935038],"iteration":98,"passed_time":2.278920277,"remaining_tim,
{"learn":[0.5,
{"learn":[0.5410284979],"iteration":99,"passed_time":2.292376773,"remaining_tim,
{"learn":[0.5,
{"learn":[0.5389789037],"iteration":100,"passed_time":2.304084305,"remaining_tim,
{"learn":[0.5,
{"learn":[0.537349429],"iteration":101,"passed_time":2.320506495,"remaining_time,
{"learn":[0.,
{"learn":[0.5355047803],"iteration":102,"passed_time":2.33167942,"remaining_time",
{"learn":[0,
{"learn":[0.5337799079],"iteration":103,"passed_time":2.34899936,"remaining_time":,
{"learn":[,
{"learn":[0.5331047334],"iteration":104,"passed_time":2.360931069,"remaining_time":,
{"learn":[,
{"learn":[0.5317501573],"iteration":105,"passed_time":2.375165487,"remaining_time":,
{"learn":[,
{"learn":[0.5300655598],"iteration":106,"passed_time":2.388947851,"remaining_time",
{"learn":[0,
{"learn":[0.5280991056],"iteration":107,"passed_time":2.403017595,"remaining_time",
{"learn":[0,
{"learn":[0.5273724892],"iteration":108,"passed_time":2.42511689,"remaining_time":,
{"learn":[,
{"learn":[0.5265662287],"iteration":109,"passed_time":2.455019415,"remaining_time":,
{"learn":,
{"learn":[0.524777615],"iteration":110,"passed_time":2.472065818,"remaining_time":19,
{"learn",
{"learn":[0.5232893771],"iteration":111,"passed_time":2.515962839,"remaining_time":1,
{"learn":,
{"learn":[0.521787377],"iteration":112,"passed_time":2.546604007,"remaining_time":19,
{"learn",
{"learn":[0.5200017943],"iteration":113,"passed_time":2.573234713,"remaining_time":,
{"learn":[,
{"learn":[0.5181597256],"iteration":114,"passed_time":2.592287484,"remaining_time",
{"learn":[0,
{"learn":[0.5167883144],"iteration":115,"passed_time":2.618533988,"remaining_time",
{"learn":[0,
{"learn":[0.5158585397],"iteration":116,"passed_time":2.874270854,"remaining_time",
{"learn":[,
{"learn":[0.514308597],"iteration":117,"passed_time":2.891056571,"remaining_time":,
{"learn":[,
{"learn":[0.5125147306],"iteration":118,"passed_time":2.907950149,"remaining_time":,
{"learn":[,
{"learn":[0.511191918],"iteration":119,"passed_time":2.920197872,"remaining_time":2,
{"learn":,
{"learn":[0.5101485213],"iteration":120,"passed_time":2.931153836,"remaining_time":,
{"learn":[,
{"learn":[0.509609957],"iteration":121,"passed_time":2.954952496,"remaining_time",
{"learn":[,
{"learn":[0.5080263746],"iteration":122,"passed_time":2.969198767,"remaining_time,
{"learn":[0,
{"learn":[0.5066043056],"iteration":123,"passed_time":2.982078143,"remaining_time",
{"learn":[0,
{"learn":[0.5052694511],"iteration":124,"passed_time":2.994762358,"remaining_time,
{"learn":[0,
{"learn":[0.5038080604],"iteration":125,"passed_time":3.009515798,"remaining_time",
{"learn":[0,
{"learn":[0.5026235345],"iteration":126,"passed_time":3.023010165,"remaining_time",
{"learn":[0,
{"learn":[0.5017630772],"iteration":127,"passed_time":3.045881945,"remaining_time",
{"learn":[0,
{"learn":[0.5005565956],"iteration":128,"passed_time":3.058384081,"remaining_time",
{"learn":[0,
{"learn":[0.4998259958],"iteration":129,"passed_time":3.080985483,"remaining_time",
{"learn":[0,
{"learn":[0.4990946122],"iteration":130,"passed_time":3.093810868,"remaining_time",
{"learn":[0,
{"learn":[0.4977383589],"iteration":131,"passed_time":3.279509767,"remaining_time",
{"learn":[,
{"learn":[0.4967383198],"iteration":132,"passed_time":3.342478126,"remaining_time":,
{"learn":[,
{"learn":[0.4956321165],"iteration":133,"passed_time":3.38443207,"remaining_time":2,
{"learn":,
{"learn":[0.4951312504],"iteration":134,"passed_time":3.440644545,"remaining_time":2,
{"learn":,
{"learn":[0.493760149],"iteration":135,"passed_time":3.507220605,"remaining_time":2,
{"learn",
{"learn":[0.4926168323],"iteration":136,"passed_time":3.560818731,"remaining_time":22,
{"learn",
{"learn":[0.4914899057],"iteration":137,"passed_time":3.6250387,"remaining_time":22,
{"learn",
{"learn":[0.489958474],"iteration":138,"passed_time":3.64640211,"remaining_time":22.5,
{"lear,
{"learn":[0.4889903805],"iteration":139,"passed_time":3.681833191,"remaining_time":22.,
{"learn,
{"learn":[0.4868201652],"iteration":140,"passed_time":3.859802885,"remaining_time":23.,
{"learn,
{"learn":[0.4860182529],"iteration":141,"passed_time":3.910140782,"remaining_time":23.,
{"learn,
{"learn":[0.4848513407],"iteration":142,"passed_time":3.976791386,"remaining_time":23.,
{"learn,
{"learn":[0.4838147722],"iteration":143,"passed_time":4.024779206,"remaining_time":23,
{"learn",
{"learn":[0.4825562826],"iteration":144,"passed_time":4.079913566,"remaining_time":24,
{"learn",
{"learn":[0.4813676469],"iteration":145,"passed_time":4.124132812,"remaining_time":24,
{"learn,
{"learn":[0.4801892001],"iteration":146,"passed_time":4.142272306,"remaining_time":24.,
{"learn,
{"learn":[0.4790185945],"iteration":147,"passed_time":4.153559473,"remaining_time":23.,
{"learn,
{"learn":[0.4784131352],"iteration":148,"passed_time":4.173011867,"remaining_time":23.,
{"learn,
{"learn":[0.4769774178],"iteration":149,"passed_time":4.186781092,"remaining_time":23,
{"learn",
{"learn":[0.4762824379],"iteration":150,"passed_time":4.205846796,"remaining_time":23,
{"learn",
{"learn":[0.4754301086],"iteration":151,"passed_time":4.224365126,"remaining_time":23,
{"learn,
{"learn":[0.4746146198],"iteration":152,"passed_time":4.238350502,"remaining_time":23.,
{"learn,
{"learn":[0.4734533839],"iteration":153,"passed_time":4.250655785,"remaining_time":23.,
{"learn,
{"learn":[0.4721579216],"iteration":154,"passed_time":4.264659004,"remaining_time":23.,
{"learn,
{"learn":[0.4715184702],"iteration":155,"passed_time":4.27729687,"remaining_time":23.,
{"learn,
{"learn":[0.4701547272],"iteration":156,"passed_time":4.296417514,"remaining_time":23.,
{"learn,
{"learn":[0.4694664988],"iteration":157,"passed_time":4.308863707,"remaining_time":22,
{"learn",
{"learn":[0.4685030236],"iteration":158,"passed_time":4.31999867,"remaining_time":22.,
{"learn,
{"learn":[0.4675089178],"iteration":159,"passed_time":4.352863448,"remaining_time":2,
{"learn",
{"learn":[0.4666139875],"iteration":160,"passed_time":4.36868181,"remaining_time":22,
{"learn",
{"learn":[0.4655020777],"iteration":161,"passed_time":4.383812561,"remaining_time":22,
{"learn,
{"learn":[0.4641886859],"iteration":162,"passed_time":4.40197279,"remaining_time":22.6,
{"lear,
{"learn":[0.4628807593],"iteration":163,"passed_time":4.413962553,"remaining_time":2,
{"learn":,
{"learn":[0.4618674926],"iteration":164,"passed_time":4.429667397,"remaining_time":,
{"learn":[,
{"learn":[0.4610802505],"iteration":165,"passed_time":4.440694396,"remaining_time":,
{"learn":[,
{"learn":[0.460497892],"iteration":166,"passed_time":4.456021765,"remaining_time":2,
{"learn",
{"learn":[0.4599133243],"iteration":167,"passed_time":4.468972057,"remaining_time":22,
{"learn",
{"learn":[0.4582726867],"iteration":168,"passed_time":4.480387553,"remaining_time":22,
{"learn,
{"learn":[0.4574641493],"iteration":169,"passed_time":4.500662466,"remaining_time":21.,
{"learn,
{"learn":[0.4569590044],"iteration":170,"passed_time":4.512580154,"remaining_time":21.,
{"learn,
{"learn":[0.4558717803],"iteration":171,"passed_time":4.526815138,"remaining_time":21,
{"learn",
{"learn":[0.4549238693],"iteration":172,"passed_time":4.538773605,"remaining_time":21,
{"learn",
{"learn":[0.4542675891],"iteration":173,"passed_time":4.551120833,"remaining_time":21,
{"learn",
{"learn":[0.4530808537],"iteration":174,"passed_time":4.564488172,"remaining_time":21,
{"learn",
{"learn":[0.4521055777],"iteration":175,"passed_time":4.576539714,"remaining_time":21,
{"learn",
{"learn":[0.4513272815],"iteration":176,"passed_time":4.604565862,"remaining_time":21,
{"learn",
{"learn":[0.4507223353],"iteration":177,"passed_time":4.627744414,"remaining_time":21,
{"learn",
{"learn":[0.4499171737],"iteration":178,"passed_time":4.648300238,"remaining_time":21,
{"learn",
{"learn":[0.4490952788],"iteration":179,"passed_time":4.673762048,"remaining_time":21,
{"learn",
{"learn":[0.4484007434],"iteration":180,"passed_time":4.699564774,"remaining_time":21,
{"learn",
{"learn":[0.4471220688],"iteration":181,"passed_time":4.720201306,"remaining_time":21,
{"learn,
{"learn":[0.4463795666],"iteration":182,"passed_time":4.733233716,"remaining_time":21,
{"learn,
{"learn":[0.4462400996],"iteration":183,"passed_time":4.754033669,"remaining_time":21,
{"learn",
{"learn":[0.4459311346],"iteration":184,"passed_time":4.771028657,"remaining_time":2,
{"learn":,
{"learn":[0.4454884501],"iteration":185,"passed_time":4.804011198,"remaining_time":,
{"learn",
{"learn":[0.4445977884],"iteration":186,"passed_time":4.837913192,"remaining_time":21,
{"learn",
{"learn":[0.4439832886],"iteration":187,"passed_time":4.861615662,"remaining_time":20,
{"learn",
{"learn":[0.4431588463],"iteration":188,"passed_time":4.892796978,"remaining_time":20,
{"learn",
{"learn":[0.4423312807],"iteration":189,"passed_time":4.923522957,"remaining_time":20,
{"learn",
{"learn":[0.4413877732],"iteration":190,"passed_time":4.946347911,"remaining_time":20,
{"learn",
{"learn":[0.4403664671],"iteration":191,"passed_time":4.968673518,"remaining_time":20,
{"learn",
{"learn":[0.4394429724],"iteration":192,"passed_time":4.998388793,"remaining_time":20,
{"learn",
{"learn":[0.439004407],"iteration":193,"passed_time":5.019981979,"remaining_time":20.,
{"learn,
{"learn":[0.4384400058],"iteration":194,"passed_time":5.039193475,"remaining_time":20.,
{"learn,
{"learn":[0.4375654113],"iteration":195,"passed_time":5.059325299,"remaining_time":20.,
{"learn,
{"learn":[0.4371537581],"iteration":196,"passed_time":5.086849063,"remaining_time":20,
{"learn",
{"learn":[0.43639314],"iteration":197,"passed_time":5.106675216,"remaining_time":20.6,
{"lear,
{"learn":[0.4362749854],"iteration":198,"passed_time":5.121664812,"remaining_time":20.,
{"learn,
{"learn":[0.4357062229],"iteration":199,"passed_time":5.133937637,"remaining_time":20.,
{"learn,
{"learn":[0.4355984441],"iteration":200,"passed_time":5.146992874,"remaining_time":20,
{"learn",
{"learn":[0.4354906633],"iteration":201,"passed_time":5.166271225,"remaining_time":2,
{"learn",
{"learn":[0.4347208502],"iteration":202,"passed_time":5.192515979,"remaining_time":20,
{"learn",
{"learn":[0.4340454236],"iteration":203,"passed_time":5.220482891,"remaining_time":2,
{"learn":,
{"learn":[0.4331170695],"iteration":204,"passed_time":5.438184255,"remaining_time":2,
{"learn":,
{"learn":[0.4324102861],"iteration":205,"passed_time":5.621248067,"remaining_time":,
{"learn":[,
{"learn":[0.4317612613],"iteration":206,"passed_time":5.732011292,"remaining_time":,
{"learn":[,
{"learn":[0.4314097493],"iteration":207,"passed_time":5.798299254,"remaining_time":,
{"learn":[,
{"learn":[0.430362233],"iteration":208,"passed_time":5.826126437,"remaining_time":2,
{"learn":,
{"learn":[0.4295173855],"iteration":209,"passed_time":5.855842124,"remaining_time":2,
{"learn":,
{"learn":[0.4290474318],"iteration":210,"passed_time":5.885358053,"remaining_time":2,
{"learn":,
{"learn":[0.4286716168],"iteration":211,"passed_time":5.907566489,"remaining_time":,
{"learn":[,
{"learn":[0.4281726674],"iteration":212,"passed_time":5.922445184,"remaining_time":,
{"learn":[,
{"learn":[0.4273850549],"iteration":213,"passed_time":5.949709159,"remaining_time":,
{"learn":[,
{"learn":[0.4267768968],"iteration":214,"passed_time":5.978810988,"remaining_time":,
{"learn":[,
{"learn":[0.4262238817],"iteration":215,"passed_time":5.995403057,"remaining_time",
{"learn":[0,
{"learn":[0.4254914934],"iteration":216,"passed_time":6.009438138,"remaining_time",
{"learn":[0,
{"learn":[0.4246021597],"iteration":217,"passed_time":6.021557649,"remaining_tim,
{"learn":[0.4,
{"learn":[0.424250028],"iteration":218,"passed_time":6.035799615,"remaining_time,
{"learn":[0.,
{"learn":[0.4231654334],"iteration":219,"passed_time":6.04885821,"remaining_time",
{"learn":[0,
{"learn":[0.4225671715],"iteration":220,"passed_time":6.078822982,"remaining_time,
{"learn":[0.,
{"learn":[0.4218089225],"iteration":221,"passed_time":6.091211117,"remaining_time,
{"learn":[0,
{"learn":[0.4209185671],"iteration":222,"passed_time":6.112043453,"remaining_time,
{"learn":[0.,
{"learn":[0.4202440879],"iteration":223,"passed_time":6.155339915,"remaining_time,
{"learn":[0.,
{"learn":[0.419926644],"iteration":224,"passed_time":6.219724063,"remaining_time",
{"learn":[0,
{"learn":[0.4195780884],"iteration":225,"passed_time":6.288808628,"remaining_time,
{"learn":[0.,
{"learn":[0.4188205343],"iteration":226,"passed_time":6.333219232,"remaining_time,
{"learn":[0.,
{"learn":[0.4180344802],"iteration":227,"passed_time":6.351282209,"remaining_time,
{"learn":[0.,
{"learn":[0.4168847632],"iteration":228,"passed_time":6.382438506,"remaining_tim,
{"learn":[0,
{"learn":[0.4162103383],"iteration":229,"passed_time":6.405191241,"remaining_time",
{"learn":[0,
{"learn":[0.4159330476],"iteration":230,"passed_time":6.425433648,"remaining_time",
{"learn":[0,
{"learn":[0.414829946],"iteration":231,"passed_time":6.447810118,"remaining_time":,
{"learn":[,
{"learn":[0.4142740235],"iteration":232,"passed_time":6.469581921,"remaining_time":,
{"learn":[,
{"learn":[0.4138186608],"iteration":233,"passed_time":6.481403361,"remaining_time",
{"learn":[,
{"learn":[0.413116042],"iteration":234,"passed_time":6.49532027,"remaining_time":21,
{"learn",
{"learn":[0.4128144884],"iteration":235,"passed_time":6.509228543,"remaining_time":2,
{"learn":,
{"learn":[0.4122866234],"iteration":236,"passed_time":6.520675415,"remaining_time":2,
{"learn":,
{"learn":[0.4117285472],"iteration":237,"passed_time":6.536116074,"remaining_time":2,
{"learn":,
{"learn":[0.4112622892],"iteration":238,"passed_time":6.548504297,"remaining_time":,
{"learn":[,
{"learn":[0.4110497734],"iteration":239,"passed_time":6.5714995,"remaining_time":2,
{"learn":,
{"learn":[0.4104382895],"iteration":240,"passed_time":6.58506327,"remaining_time":20,
{"learn",
{"learn":[0.4096880977],"iteration":241,"passed_time":6.600510743,"remaining_time":,
{"learn":[,
{"learn":[0.4092220255],"iteration":242,"passed_time":6.612133786,"remaining_time":,
{"learn":[,
{"learn":[0.4085824487],"iteration":243,"passed_time":6.625529951,"remaining_time",
{"learn":[0,
{"learn":[0.4075276933],"iteration":244,"passed_time":6.639327742,"remaining_time,
{"learn":[0.,
{"learn":[0.4065598866],"iteration":245,"passed_time":6.652569597,"remaining_tim,
{"learn":[0.3,
{"learn":[0.4061992539],"iteration":246,"passed_time":6.671193574,"remaining_tim,
{"learn":[0.3,
{"learn":[0.4055114373],"iteration":247,"passed_time":6.682748948,"remaining_,
{"learn":[0.3941,
{"learn":[0.4051584814],"iteration":248,"passed_time":6.699859303,"remaini,
{"learn":[0.3936636,
{"learn":[0.404716108],"iteration":249,"passed_time":6.710976936,"remainin,
{"learn":[0.392939,
{"learn":[0.4044089509],"iteration":250,"passed_time":6.725273452,"remainin,
{"learn":[0.392058,
{"learn":[0.4040045908],"iteration":251,"passed_time":6.764973572,"remai,
{"learn":[0.391575900,
{"learn":[0.4034804302],"iteration":252,"passed_time":6.796584127,"remai,
{"learn":[0.391300189,
{"learn":[0.4031007561],"iteration":253,"passed_time":6.817635907,"remai,
{"learn":[0.390716654,
{"learn":[0.4024575091],"iteration":254,"passed_time":6.840734297,"remai,
{"learn":[0.390278461,
{"learn":[0.4015910984],"iteration":255,"passed_time":6.884216467,"rema,
{"learn":[0.3897482396,
{"learn":[0.4010713446],"iteration":256,"passed_time":6.919225198,"rema,
{"learn":[0.3889646726,
{"learn":[0.4005390483],"iteration":257,"passed_time":6.987264738,"rema,
{"learn":[0.3884412941,
{"learn":[0.3999778346],"iteration":258,"passed_time":7.033241197,"rema,
{"learn":[0.3883187324,
{"learn":[0.399615089],"iteration":259,"passed_time":7.067444493,"rema,
{"learn":[0.3880549395,
{"learn":[0.3993201018],"iteration":260,"passed_time":7.098055412,"rem,
{"learn":[0.3876541602],
{"learn":[0.3987924716],"iteration":261,"passed_time":7.11870884,"rema,
{"learn":[0.3868604623,
{"learn":[0.3983791391],"iteration":262,"passed_time":7.13814425,"remai,
{"learn":[0.386799017,
{"learn":[0.3977369242],"iteration":263,"passed_time":7.165761444,"remai,
{"learn":[0.386325605,
{"learn":[0.3971429017],"iteration":264,"passed_time":7.182490091,"remai,
{"learn":[0.38581961,
{"learn":[0.3967844513],"iteration":265,"passed_time":7.205481445,"remain,
{"learn":[0.38537386,
{"learn":[0.3962576972],"iteration":266,"passed_time":7.228278261,"rema,
{"learn":[0.3847155624,
{"learn":[0.3955429334],"iteration":267,"passed_time":7.247949135,"rema,
{"learn":[0.38416909],,
{"learn":[0.3951263817],"iteration":268,"passed_time":7.278786953,"re,
{"learn":[0.3838975421],
{"learn":[0.3947788396],"iteration":269,"passed_time":7.305519397,"r,
{"learn":[0.3833409082],",
{"learn":[0.3942107948],"iteration":270,"passed_time":7.334858626,",
{"learn":[0.3827020174],"i,
{"learn":[0.3934489192],"iteration":271,"passed_time":7.372597766,",
{"learn":[0.3826092795],"i,
{"learn":[0.3927063239],"iteration":272,"passed_time":7.396294409,",
{"learn":[0.3823645545],",
{"learn":[0.3923755142],"iteration":273,"passed_time":7.430227099,"r,
{"learn":[0.3819809337],",
{"learn":[0.391913311],"iteration":274,"passed_time":7.461036621,"re,
{"learn":[0.3813536555],,
{"learn":[0.3914535994],"iteration":275,"passed_time":7.478595175,"re,
{"learn":[0.3807963554],,
{"learn":[0.3909107771],"iteration":276,"passed_time":7.499949525,"r,
{"learn":[0.3802185284],",
{"learn":[0.3906974335],"iteration":277,"passed_time":7.519711963,",
{"learn":[0.3797544641],"i,
{"learn":[0.3902262497],"iteration":278,"passed_time":7.536889135,",
{"learn":[0.3792561346],"i,
{"learn":[0.3897838848],"iteration":279,"passed_time":7.569804841,",
{"learn":[0.3788974361],"i,
{"learn":[0.3892794054],"iteration":280,"passed_time":7.589226649,",
{"learn":[0.3785588483],"i,
{"learn":[0.3889564585],"iteration":281,"passed_time":7.600399051,",
{"learn":[0.3781237305],"i,
{"learn":[0.3887333706],"iteration":282,"passed_time":7.613015765,",
{"learn":[0.3777247874],"i,
{"learn":[0.3882791671],"iteration":283,"passed_time":7.628398784,",
{"learn":[0.377197422],"it,
{"learn":[0.387958033],"iteration":284,"passed_time":7.639318948,",
{"learn":[0.3765539677],"i,
{"learn":[0.3875895172],"iteration":285,"passed_time":7.660826762,,
{"learn":[0.375777773],"it,
{"learn":[0.3868103347],"iteration":286,"passed_time":7.6729167,"r,
{"learn":[0.3754268431],",
{"learn":[0.3866046734],"iteration":287,"passed_time":7.685752316,"r,
{"learn":[0.3748975493],",
{"learn":[0.3860666786],"iteration":288,"passed_time":7.697263774,",
{"learn":[0.3745492824],"i,
{"learn":[0.3857079933],"iteration":289,"passed_time":7.709745104,",
{"learn":[0.3740561399],"i,
{"learn":[0.3851814454],"iteration":290,"passed_time":7.728671232,
{"learn":[0.373440844],"iter,
{"learn":[0.3848006827],"iteration":291,"passed_time":7.74227025,
{"learn":[0.3731734284],"ite,
{"learn":[0.3843123386],"iteration":292,"passed_time":7.76374767,
{"learn":[0.3725313261],"iter,
{"learn":[0.3837418661],"iteration":293,"passed_time":7.77679467,
{"learn":[0.3722381924],"ite,
{"learn":[0.3833790367],"iteration":294,"passed_time":7.795239264,
{"learn":[0.371863773],"iter,
{"learn":[0.3828834833],"iteration":295,"passed_time":7.80742649,
{"learn":[0.3715085603],"iter,
{"learn":[0.3823659437],"iteration":296,"passed_time":7.82356889,
{"learn":[0.37117357],"iterat,
{"learn":[0.3818879109],"iteration":297,"passed_time":7.850029,
{"learn":[0.3706455782],"itera,
{"learn":[0.3812846786],"iteration":298,"passed_time":7.8632807,
{"learn":[0.3701945027],"itera,
{"learn":[0.380872642],"iteration":299,"passed_time":7.87460117,
{"learn":[0.369722952],"ite,
{"learn":[0.3804658254],"iteration":300,"passed_time":7.888140583,
{"learn":[0.3692692463],"ite,
{"learn":[0.3800982611],"iteration":301,"passed_time":7.901360448,
{"learn":[0.3688427429],"ite,
{"learn":[0.3796742148],"iteration":302,"passed_time":7.920434232,
{"learn":[0.3684839069],"ite,
{"learn":[0.3794669987],"iteration":303,"passed_time":7.937985969,
{"learn":[0.368037094],"iter,
{"learn":[0.3788243026],"iteration":304,"passed_time":7.95295634,
{"learn":[0.3677833008],"iter,
{"learn":[0.3785542892],"iteration":305,"passed_time":7.96620632,
{"learn":[0.3674409432],"iter,
{"learn":[0.3780734192],"iteration":306,"passed_time":7.98130556,
{"learn":[0.3671160432],"iter,
{"learn":[0.3777417086],"iteration":307,"passed_time":7.99230615,
{"learn":[0.3667015281],"ite,
{"learn":[0.3772342427],"iteration":308,"passed_time":8.013046462,
{"learn":[0.3665694946],"ite,
{"learn":[0.3767275607],"iteration":309,"passed_time":8.03258391,,
{"learn":[0.3660631255],"it,
{"learn":[0.3763999642],"iteration":310,"passed_time":8.062215137,,
{"learn":[0.3655838139],"i,
{"learn":[0.3758361356],"iteration":311,"passed_time":8.084343758,",
{"learn":[0.3652460266],"i,
{"learn":[0.3755132268],"iteration":312,"passed_time":8.108443689,",
{"learn":[0.3647037104],",
{"learn":[0.3750377782],"iteration":313,"passed_time":8.124637968,"r,
{"learn":[0.3642846341],",
{"learn":[0.3745407629],"iteration":314,"passed_time":8.156141188,"r,
{"learn":[0.3637736028],",
{"learn":[0.3740166129],"iteration":315,"passed_time":8.190796196,"r,
{"learn":[0.3633503326],",
{"learn":[0.3734777961],"iteration":316,"passed_time":8.216956399,"r,
{"learn":[0.3628210509],",
{"learn":[0.3728045571],"iteration":317,"passed_time":8.255487575,,
{"learn":[0.3623826836],"it,
{"learn":[0.3723791036],"iteration":318,"passed_time":8.289005416,
{"learn":[0.3619304194],"ite,
{"learn":[0.3720373291],"iteration":319,"passed_time":8.317851509,
{"learn":[0.3616469529],"ite,
{"learn":[0.3717131869],"iteration":320,"passed_time":8.337119342,
{"learn":[0.36124373],"itera,
{"learn":[0.3711020048],"iteration":321,"passed_time":8.3593088,
{"learn":[0.360728052],"iterat,
{"learn":[0.3707327798],"iteration":322,"passed_time":8.3770,
{"learn":[0.3602785665],"iteratio,
{"learn":[0.3703961939],"iteration":323,"passed_time":8.3915,
{"learn":[0.3600347284],"iteratio,
{"learn":[0.370192907],"iteration":324,"passed_time":8.41638,
{"learn":[0.3597121687],"itera,
{"learn":[0.370036576],"iteration":325,"passed_time":8.44748776,
{"learn":[0.3593398485],"ite,
{"learn":[0.3697646004],"iteration":326,"passed_time":8.47271379,
{"learn":[0.3591026906],"ite,
{"learn":[0.3694583802],"iteration":327,"passed_time":8.494413908,
{"learn":[0.3587335089],"ite,
{"learn":[0.3689920492],"iteration":328,"passed_time":8.516319631,
{"learn":[0.3582781339],"ite,
{"learn":[0.3686262195],"iteration":329,"passed_time":8.544912487,
{"learn":[0.3579357395],"ite,
{"learn":[0.368246473],"iteration":330,"passed_time":8.577897617,,
{"learn":[0.3578677509],"it,
{"learn":[0.3677227159],"iteration":331,"passed_time":8.604429734,,
{"learn":[0.3573337372],"i,
{"learn":[0.3676399517],"iteration":332,"passed_time":8.628377362,",
{"learn":[0.3571324697],"i,
{"learn":[0.3672676848],"iteration":333,"passed_time":8.657241518,,
{"learn":[0.3568473888],"it,
{"learn":[0.3668784944],"iteration":334,"passed_time":8.677837406,,
{"learn":[0.3564493867],"it,
{"learn":[0.3664060773],"iteration":335,"passed_time":8.718560582,,
{"learn":[0.3560707432],"it,
{"learn":[0.3658866457],"iteration":336,"passed_time":8.750243695,,
{"learn":[0.3555782358],"it,
{"learn":[0.3654196303],"iteration":337,"passed_time":8.774095444,,
{"learn":[0.3553549033],"it,
{"learn":[0.3650670244],"iteration":338,"passed_time":8.788540203,,
{"learn":[0.3550917089],"it,
{"learn":[0.364623387],"iteration":339,"passed_time":8.812418275,",
{"learn":[0.3547024859],,
{"learn":[0.364137815],"iteration":340,"passed_time":8.83967677,"rema,
{"learn":[0.3542580222,
{"learn":[0.3636323395],"iteration":341,"passed_time":8.857115204,"rema,
{"learn":[0.3539643782,
{"learn":[0.363223376],"iteration":342,"passed_time":8.877355777,"remai,
{"learn":[0.353549533,
{"learn":[0.3627281735],"iteration":343,"passed_time":8.895625725,"rema,
{"learn":[0.353346936],
{"learn":[0.3624658493],"iteration":344,"passed_time":8.913228712,"rem,
{"learn":[0.352829568],,
{"learn":[0.3620058573],"iteration":345,"passed_time":8.943004617,"re,
{"learn":[0.3523964835],,
{"learn":[0.361890503],"iteration":346,"passed_time":8.967308422,"rem,
{"learn":[0.3520122722],
{"learn":[0.3614614661],"iteration":347,"passed_time":8.984609818,"re,
{"learn":[0.351581935],",
{"learn":[0.3611025968],"iteration":348,"passed_time":9.001993059,",
{"learn":[0.3512200125],"i,
{"learn":[0.3606710949],"iteration":349,"passed_time":9.01289001,"r,
{"learn":[0.3509536683],,
{"learn":[0.3603531481],"iteration":350,"passed_time":9.032746727,"re,
{"learn":[0.3505532739],,
{"learn":[0.3601776189],"iteration":351,"passed_time":9.045134538,"r,
{"learn":[0.3501131597],,
{"learn":[0.3598555777],"iteration":352,"passed_time":9.060562544,"r,
{"learn":[0.3497488632],",
{"learn":[0.3595747686],"iteration":353,"passed_time":9.074854052,"r,
{"learn":[0.3494308715],",
{"learn":[0.3592592218],"iteration":354,"passed_time":9.092839569,"r,
{"learn":[0.3491990084],",
{"learn":[0.3589350411],"iteration":355,"passed_time":9.114182268,"r,
{"learn":[0.3488967931],",
{"learn":[0.3586518054],"iteration":356,"passed_time":9.136509604,"r,
{"learn":[0.3488498626],",
{"learn":[0.3581739852],"iteration":357,"passed_time":9.167942332,",
{"learn":[0.3485150417],"i,
{"learn":[0.3579271636],"iteration":358,"passed_time":9.18273776,"r,
{"learn":[0.3480458032],",
{"learn":[0.3576167677],"iteration":359,"passed_time":9.205016776,"r,
{"learn":[0.3475705144],",
{"learn":[0.3571220049],"iteration":360,"passed_time":9.229595342,"r,
{"learn":[0.3472120983],",
{"learn":[0.3567437512],"iteration":361,"passed_time":9.247526298,",
{"learn":[0.3469945075],"i,
{"learn":[0.3563123497],"iteration":362,"passed_time":9.264857682,",
{"learn":[0.3469642062],"i,
{"learn":[0.3559546244],"iteration":363,"passed_time":9.27991329,"r,
{"learn":[0.3465841871],",
{"learn":[0.3556558292],"iteration":364,"passed_time":9.293777121,",
{"learn":[0.3463274836],"i,
{"learn":[0.3553582572],"iteration":365,"passed_time":9.310466184,",
{"learn":[0.3460099314],"i,
{"learn":[0.3550309801],"iteration":366,"passed_time":9.332421432,",
{"learn":[0.3457956995],",
{"learn":[0.3547832172],"iteration":367,"passed_time":9.345292779,"r,
{"learn":[0.3454647424],",
{"learn":[0.3543782974],"iteration":368,"passed_time":9.360698485,"r,
{"learn":[0.3451095471],",
{"learn":[0.3539539504],"iteration":369,"passed_time":9.372721621,",
{"learn":[0.344796354],"it,
{"learn":[0.3538776127],"iteration":370,"passed_time":9.386125371,,
{"learn":[0.344388492],"ite,
{"learn":[0.3535628229],"iteration":371,"passed_time":9.415480091,
{"learn":[0.3439918004],"ite,
{"learn":[0.3533322651],"iteration":372,"passed_time":9.440396982,
{"learn":[0.3437910014],"it,
{"learn":[0.3531637143],"iteration":373,"passed_time":9.466019562,
{"learn":[0.3436924837],"ite,
{"learn":[0.3528165831],"iteration":374,"passed_time":9.48830681,
{"learn":[0.3435370312],"iter,
{"learn":[0.352322593],"iteration":375,"passed_time":9.514683318,
{"learn":[0.3432468973],"ite,
{"learn":[0.3520554659],"iteration":376,"passed_time":9.530544152,
{"learn":[0.3429691207],"ite,
{"learn":[0.3516750289],"iteration":377,"passed_time":9.544709088,
{"learn":[0.342721483],"iter,
{"learn":[0.3513862154],"iteration":378,"passed_time":9.55908344,
{"learn":[0.3422765154],"iter,
{"learn":[0.3508687067],"iteration":379,"passed_time":9.57442442,
{"learn":[0.3419686025],"iter,
{"learn":[0.3508051263],"iteration":380,"passed_time":9.59431584,
{"learn":[0.3416893612],"ite,
{"learn":[0.3503932208],"iteration":381,"passed_time":9.612289795,
{"learn":[0.3414214168],"it,
{"learn":[0.3501380457],"iteration":382,"passed_time":9.636235991,,
{"learn":[0.3412102097],"i,
{"learn":[0.3498111861],"iteration":383,"passed_time":9.657406764,",
{"learn":[0.3409183255],"i,
{"learn":[0.3494981399],"iteration":384,"passed_time":9.676410983,",
{"learn":[0.3405163616],"i,
{"learn":[0.3491578834],"iteration":385,"passed_time":9.697760634,",
{"learn":[0.3403048141],"i,
{"learn":[0.3488842875],"iteration":386,"passed_time":9.720383237,",
{"learn":[0.3399162731],"i,
{"learn":[0.348668958],"iteration":387,"passed_time":9.732387371,"r,
{"learn":[0.3395035623],",
{"learn":[0.3482609301],"iteration":388,"passed_time":9.744751138,"r,
{"learn":[0.3391646346],
{"learn":[0.3481553443],"iteration":389,"passed_time":9.759208383,"rem,
{"learn":[0.3390392451],
{"learn":[0.3475975386],"iteration":390,"passed_time":9.770306795,"rem,
{"learn":[0.3387716987],
{"learn":[0.3472826892],"iteration":391,"passed_time":9.784116088,"rem,
{"learn":[0.3384774791],
{"learn":[0.3469779907],"iteration":392,"passed_time":9.79852876,"rema,
{"learn":[0.338205863,
{"learn":[0.3465613608],"iteration":393,"passed_time":9.813829812,"remai,
{"learn":[0.337967233,
{"learn":[0.3462322329],"iteration":394,"passed_time":9.828739141,"rem,
{"learn":[0.337733658],,
{"learn":[0.3459965127],"iteration":395,"passed_time":9.842817733,"re,
{"learn":[0.3375695482],
{"learn":[0.3456589167],"iteration":396,"passed_time":9.85632627,"rema,
{"learn":[0.3373365874,
{"learn":[0.3452962717],"iteration":397,"passed_time":9.870210632,"rem,
{"learn":[0.3370092352],
{"learn":[0.3448549117],"iteration":398,"passed_time":9.884614663,"rem,
{"learn":[0.3369862688],
{"learn":[0.3445823654],"iteration":399,"passed_time":9.896846529,"re,
{"learn":[0.3367400535],,
{"learn":[0.3442595036],"iteration":400,"passed_time":9.918034649,"re,
{"learn":[0.3364045719],,
{"learn":[0.3439337719],"iteration":401,"passed_time":9.937107104,"re,
{"learn":[0.3361846594],
{"learn":[0.343549575],"iteration":402,"passed_time":9.952259928,"rem,
{"learn":[0.3361625201],
{"learn":[0.3431561238],"iteration":403,"passed_time":9.966711925,"rem,
{"learn":[0.3358363853,
{"learn":[0.3429068698],"iteration":404,"passed_time":9.987962534,"rema,
{"learn":[0.3355340036,
{"learn":[0.3424974957],"iteration":405,"passed_time":10.00135512,"rema,
{"learn":[0.3351637782,
{"learn":[0.3421292878],"iteration":406,"passed_time":10.01861404,"rem,
{"learn":[0.3349197083],
{"learn":[0.3419325496],"iteration":407,"passed_time":10.03027083,"rem,
{"learn":[0.3345989761,
{"learn":[0.341650278],"iteration":408,"passed_time":10.04570228,"remai,
{"learn":[0.334427911,
{"learn":[0.3413200009],"iteration":409,"passed_time":10.05630121,"rema,
{"learn":[0.3343841963,
{"learn":[0.3409283798],"iteration":410,"passed_time":10.06904965,"rema,
{"learn":[0.334357118,
{"learn":[0.3406441973],"iteration":411,"passed_time":10.09233539,"remai,
{"learn":[0.33407752,
{"learn":[0.3404049154],"iteration":412,"passed_time":10.11824467,"remain,
{"learn":[0.33377381,
{"learn":[0.3400400757],"iteration":413,"passed_time":10.13531738,"remain,
{"learn":[0.33367628,
{"learn":[0.3397825388],"iteration":414,"passed_time":10.1494522,"remaini,
{"learn":[0.3334068,
{"learn":[0.3394817079],"iteration":415,"passed_time":10.16270727,"remaini,
{"learn":[0.3333056,
{"learn":[0.3392180307],"iteration":416,"passed_time":10.17712153,"remaini,
{"learn":[0.3330911,
{"learn":[0.3388907756],"iteration":417,"passed_time":10.1901987,"remainin,
{"learn":[0.332878,
{"learn":[0.3385752379],"iteration":418,"passed_time":10.21893655,"remainin,
{"learn":[0.33257,
{"learn":[0.3383301786],"iteration":419,"passed_time":10.24183459,"remaining,
{"learn":[0.33235,
{"learn":[0.3380912413],"iteration":420,"passed_time":10.25690961,"remaining,
{"learn":[0.33202,
{"learn":[0.3378739318],"iteration":421,"passed_time":10.27885926,"remainin,
{"learn":[0.331800,
{"learn":[0.337455527],"iteration":422,"passed_time":10.30172721,"remaining,
{"learn":[0.33154,
{"learn":[0.3372323646],"iteration":423,"passed_time":10.31978192,"remaining,
{"learn":[0.33136,
{"learn":[0.3369235714],"iteration":424,"passed_time":10.33850916,"remaining,
{"learn":[0.33107,
{"learn":[0.3365501774],"iteration":425,"passed_time":10.35487107,"remaining,
{"learn":[0.33081,
{"learn":[0.3362375171],"iteration":426,"passed_time":10.38210918,"remaining,
{"learn":[0.33066,
{"learn":[0.3360307745],"iteration":427,"passed_time":10.39648414,"remaining,
{"learn":[0.33036,
{"learn":[0.3357483763],"iteration":428,"passed_time":10.41301144,"remaining,
{"learn":[0.3301,
{"learn":[0.3353809951],"iteration":429,"passed_time":10.42632247,"remaining_,
{"learn":[0.3298,
{"learn":[0.3351661817],"iteration":430,"passed_time":10.43797241,"remaining,
{"learn":[0.32966,
{"learn":[0.3349479135],"iteration":431,"passed_time":10.45059476,"remaining,
{"learn":[0.32941,
{"learn":[0.3346840784],"iteration":432,"passed_time":10.46340336,"remaining,
{"learn":[0.32919,
{"learn":[0.334203673],"iteration":433,"passed_time":10.4758555,"remaining_t,
{"learn":[0.328,
{"learn":[0.3338727576],"iteration":434,"passed_time":10.4902474,"remaining_ti,
{"learn":[0.32,
{"learn":[0.3336868977],"iteration":435,"passed_time":10.5061233,"remaining_tim,
{"learn":[0.3,
{"learn":[0.3333648837],"iteration":436,"passed_time":10.51950815,"remaining_ti,
{"learn":[0.32,
{"learn":[0.3331380234],"iteration":437,"passed_time":10.53587346,"remaining_ti,
{"learn":[0.32,
{"learn":[0.3329660694],"iteration":438,"passed_time":10.5463575,"remaining_tim,
{"learn":[0.3,
{"learn":[0.3328635536],"iteration":439,"passed_time":10.56059225,"remaining_ti,
{"learn":[0.32,
{"learn":[0.332596479],"iteration":440,"passed_time":10.57425887,"remaining_tim,
{"learn":[0.,
{"learn":[0.3322380575],"iteration":441,"passed_time":10.58570373,"remaining_tim,
{"learn":[0.3,
{"learn":[0.332101826],"iteration":442,"passed_time":10.60693242,"remaining_time,
{"learn":[0.,
{"learn":[0.3317973964],"iteration":443,"passed_time":10.62726802,"remaining_time,
{"learn":[0.,
{"learn":[0.3315440643],"iteration":444,"passed_time":10.64229853,"remaining_tim,
{"learn":[0.3,
{"learn":[0.331408052],"iteration":445,"passed_time":10.65771137,"remaining_time,
{"learn":[0.,
{"learn":[0.3311445469],"iteration":446,"passed_time":10.6717999,"remaining_time,
{"learn":[0.,
{"learn":[0.3309421003],"iteration":447,"passed_time":10.68927161,"remaining_time,
{"learn":[0.,
{"learn":[0.3307655394],"iteration":448,"passed_time":10.70270568,"remaining_tim,
{"learn":[0.,
{"learn":[0.3306917211],"iteration":449,"passed_time":10.7221959,"remaining_time",
{"learn":[,
{"learn":[0.3303575732],"iteration":450,"passed_time":10.73804355,"remaining_time":,
{"learn":[,
{"learn":[0.330108551],"iteration":451,"passed_time":10.75641449,"remaining_time":1,
{"learn":,
{"learn":[0.3299166691],"iteration":452,"passed_time":10.77523773,"remaining_time":1,
{"learn":,
{"learn":[0.3295261947],"iteration":453,"passed_time":10.80099112,"remaining_time",
{"learn":[0,
{"learn":[0.3291483586],"iteration":454,"passed_time":10.82139514,"remaining_time",
{"learn":[0,
{"learn":[0.3289839156],"iteration":455,"passed_time":10.84200638,"remaining_time",
{"learn":[,
{"learn":[0.3288508975],"iteration":456,"passed_time":10.86561951,"remaining_time":,
{"learn":[,
{"learn":[0.3285931832],"iteration":457,"passed_time":10.89769832,"remaining_time":,
{"learn":[,
{"learn":[0.3282674621],"iteration":458,"passed_time":10.91950365,"remaining_time":,
{"learn":[,
{"learn":[0.3280020137],"iteration":459,"passed_time":10.94053305,"remaining_tim,
{"learn":[0.3,
{"learn":[0.3277558338],"iteration":460,"passed_time":10.96600942,"remaining_tim,
{"learn":[0.3,
{"learn":[0.3275627343],"iteration":461,"passed_time":10.99356025,"remaining_ti,
{"learn":[0.32,
{"learn":[0.3272166813],"iteration":462,"passed_time":11.01883159,"remaining_ti,
{"learn":[0.32,
{"learn":[0.3268499685],"iteration":463,"passed_time":11.04128394,"remaining_t,
{"learn":[0.321,
{"learn":[0.3264900202],"iteration":464,"passed_time":11.06611035,"remaining_t,
{"learn":[0.321,
{"learn":[0.3261866472],"iteration":465,"passed_time":11.09652078,"remaining_t,
{"learn":[0.320,
{"learn":[0.325890277],"iteration":466,"passed_time":11.12057311,"remaining_ti,
{"learn":[0.32,
{"learn":[0.3256213483],"iteration":467,"passed_time":11.13991008,"remaining_t,
{"learn":[0.320,
{"learn":[0.3254741895],"iteration":468,"passed_time":11.15842163,"remaining_,
{"learn":[0.3202,
{"learn":[0.3252834807],"iteration":469,"passed_time":11.17629105,"remaining_,
{"learn":[0.3200,
{"learn":[0.3250640382],"iteration":470,"passed_time":11.19999544,"remainin,
{"learn":[0.319750,
{"learn":[0.3250012439],"iteration":471,"passed_time":11.22267793,"remainin,
{"learn":[0.319339,
{"learn":[0.3246897996],"iteration":472,"passed_time":11.24092175,"remainin,
{"learn":[0.318998,
{"learn":[0.3244252786],"iteration":473,"passed_time":11.27216891,"remainin,
{"learn":[0.318851,
{"learn":[0.3241636889],"iteration":474,"passed_time":11.30704214,"remaini,
{"learn":[0.3185812,
{"learn":[0.3238849322],"iteration":475,"passed_time":11.32935576,"remai,
{"learn":[0.31841098,
{"learn":[0.3235836223],"iteration":476,"passed_time":11.35585605,"remain,
{"learn":[0.31817222,
{"learn":[0.3233070898],"iteration":477,"passed_time":11.38527154,"remain,
{"learn":[0.31790632,
{"learn":[0.3230861677],"iteration":478,"passed_time":11.41259278,"remain,
{"learn":[0.31762100,
{"learn":[0.3228753008],"iteration":479,"passed_time":11.45984349,"remai,
{"learn":[0.317331768,
{"learn":[0.3226810989],"iteration":480,"passed_time":11.6540916,"remai,
{"learn":[0.317020650,
{"learn":[0.322539431],"iteration":481,"passed_time":11.73800018,"remain,
{"learn":[0.31664449,
{"learn":[0.3223393722],"iteration":482,"passed_time":11.81926357,"remai,
{"learn":[0.316431108,
{"learn":[0.3221575562],"iteration":483,"passed_time":11.84391684,"rema,
{"learn":[0.3161558933,
{"learn":[0.3219743654],"iteration":484,"passed_time":11.91272842,"rema,
{"learn":[0.3159303971,
{"learn":[0.3217735912],"iteration":485,"passed_time":11.96313384,"rema,
{"learn":[0.3157106873,
{"learn":[0.3214725071],"iteration":486,"passed_time":12.04067696,"rema,
{"learn":[0.3153982957,
{"learn":[0.3212125032],"iteration":487,"passed_time":12.05523885,"rema,
{"learn":[0.3152485609,
{"learn":[0.3210574478],"iteration":488,"passed_time":12.08427647,"rema,
{"learn":[0.3149483148,
{"learn":[0.3208545693],"iteration":489,"passed_time":12.09805478,"rema,
{"learn":[0.3146336682,
{"learn":[0.3205892039],"iteration":490,"passed_time":12.11321973,"rema,
{"learn":[0.3144246081,
{"learn":[0.3203131842],"iteration":491,"passed_time":12.12546839,"rema,
{"learn":[0.3141898998,
{"learn":[0.3200656655],"iteration":492,"passed_time":12.13962682,"rem,
{"learn":[0.3138907375],
{"learn":[0.3197218163],"iteration":493,"passed_time":12.15257024,"rem,
{"learn":[0.313639994],,
{"learn":[0.3195452317],"iteration":494,"passed_time":12.16567816,"re,
{"learn":[0.3133818023],,
{"learn":[0.3193145707],"iteration":495,"passed_time":12.18391908,"re,
{"learn":[0.3131483732],
{"learn":[0.3189792109],"iteration":496,"passed_time":12.19612215,"rem,
{"learn":[0.3127467293],
{"learn":[0.3187213541],"iteration":497,"passed_time":12.21699888,"re,
{"learn":[0.3124860368],,
{"learn":[0.3185122714],"iteration":498,"passed_time":12.23022969,"r,
{"learn":[0.3124047556],",
{"learn":[0.3181637233],"iteration":499,"passed_time":12.24618271,"r,
{"learn":[0.3121492191],",
{"learn":[0.3179998529],"iteration":500,"passed_time":12.25768296,"r,
{"learn":[0.3119845955],,
{"learn":[0.3177410869],"iteration":501,"passed_time":12.28117501,"r,
{"learn":[0.311810693],"i,
{"learn":[0.3174270662],"iteration":502,"passed_time":12.29758229,",
{"learn":[0.31163355],"ite,
{"learn":[0.3170736065],"iteration":503,"passed_time":12.3323125,
{"learn":[0.3114242344],"iter,
{"learn":[0.3168650774],"iteration":504,"passed_time":12.3548895,
{"learn":[0.3112069816],"ite,
{"learn":[0.3165916152],"iteration":505,"passed_time":12.38273967,
{"learn":[0.3110996808],"ite,
{"learn":[0.3163867847],"iteration":506,"passed_time":12.3988707,
{"learn":[0.3109515229],"iter,
{"learn":[0.3161270026],"iteration":507,"passed_time":12.41215,
{"learn":[0.3108671258],"iterat,
{"learn":[0.3159484511],"iteration":508,"passed_time":12.44015,
{"learn":[0.3106421291],"iterat,
{"learn":[0.3157577203],"iteration":509,"passed_time":12.520,
{"learn":[0.3103204521],"iteratio,
{"learn":[0.315589502],"iteration":510,"passed_time":12.5857,
{"learn":[0.3101404992],"iter,
{"learn":[0.3151908126],"iteration":511,"passed_time":12.6381505,
{"learn":[0.3098828513],"iter,
{"learn":[0.3149868243],"iteration":512,"passed_time":12.6533870,
{"learn":[0.3097179335],"iter,
{"learn":[0.314816982],"iteration":513,"passed_time":12.67532373,
{"learn":[0.3094807887],"ite,
{"learn":[0.3146997372],"iteration":514,"passed_time":12.73734896,
{"learn":[0.3092579086],"ite,
{"learn":[0.3144023782],"iteration":515,"passed_time":12.77329398,
{"learn":[0.3090465771],"ite,
{"learn":[0.3142021728],"iteration":516,"passed_time":12.78510813,
{"learn":[0.3088382669],"ite,
{"learn":[0.3139803356],"iteration":517,"passed_time":12.80466715,
{"learn":[0.3085398647],"it,
{"learn":[0.3137608296],"iteration":518,"passed_time":12.81620428,,
{"learn":[0.3083949739],"it,
{"learn":[0.31341057],"iteration":519,"passed_time":12.83411565,"r,
{"learn":[0.3080479725],",
{"learn":[0.3130907114],"iteration":520,"passed_time":12.85314443,"r,
{"learn":[0.3078569891],",
{"learn":[0.3128264556],"iteration":521,"passed_time":12.87232449,"r,
{"learn":[0.307539853],"i,
{"learn":[0.3126038572],"iteration":522,"passed_time":12.88587204,",
{"learn":[0.3073178971],"i,
{"learn":[0.312353831],"iteration":523,"passed_time":12.91308226,"r,
{"learn":[0.3071476213],,
{"learn":[0.3120547713],"iteration":524,"passed_time":12.93045865,"re,
{"learn":[0.3069687745],
{"learn":[0.3118085311],"iteration":525,"passed_time":12.94400201,"rem,
{"learn":[0.3069135836],
{"learn":[0.3115777316],"iteration":526,"passed_time":12.95722545,"rem,
{"learn":[0.306627271],,
{"learn":[0.3114092746],"iteration":527,"passed_time":12.97726238,"re,
{"learn":[0.3064243156],,
{"learn":[0.3112114559],"iteration":528,"passed_time":12.98879287,"re,
{"learn":[0.3061919203],,
{"learn":[0.3109588784],"iteration":529,"passed_time":13.018981,"rema,
{"learn":[0.3059663759,
{"learn":[0.3107749128],"iteration":530,"passed_time":13.03300401,"rema,
{"learn":[0.3057223618,
{"learn":[0.3105429804],"iteration":531,"passed_time":13.04578496,"rema,
{"learn":[0.305480445],
{"learn":[0.3102318785],"iteration":532,"passed_time":13.061653,"remai,
{"learn":[0.305188864,
{"learn":[0.3100751226],"iteration":533,"passed_time":13.08176734,"rema,
{"learn":[0.3049512808,
{"learn":[0.3098648006],"iteration":534,"passed_time":13.10275465,"rema,
{"learn":[0.3047623194,
{"learn":[0.3095545962],"iteration":535,"passed_time":13.12344067,"rema,
{"learn":[0.3044993814,
{"learn":[0.3094350067],"iteration":536,"passed_time":13.14766241,"rem,
{"learn":[0.3043106347],
{"learn":[0.3091542756],"iteration":537,"passed_time":13.16694501,"rem,
{"learn":[0.3041345827],
{"learn":[0.3090762197],"iteration":538,"passed_time":13.17936329,"rem,
{"learn":[0.3038950294,
{"learn":[0.3087981827],"iteration":539,"passed_time":13.19487514,"rema,
{"learn":[0.303601238],
{"learn":[0.308592982],"iteration":540,"passed_time":13.20661293,"rema,
{"learn":[0.3033990915,
{"learn":[0.3084789597],"iteration":541,"passed_time":13.22007401,"re,
{"learn":[0.3031145593],,
{"learn":[0.308386983],"iteration":542,"passed_time":13.2352154,"rema,
{"learn":[0.3028960694,
{"learn":[0.3081175344],"iteration":543,"passed_time":13.2463193,"remai,
{"learn":[0.302704582,
{"learn":[0.3079433739],"iteration":544,"passed_time":13.26905623,"remai,
{"learn":[0.302472912,
{"learn":[0.3077897954],"iteration":545,"passed_time":13.28720834,"remai,
{"learn":[0.302246920,
{"learn":[0.307526383],"iteration":546,"passed_time":13.30477837,"remain,
{"learn":[0.30205485,
{"learn":[0.3073204239],"iteration":547,"passed_time":13.32176882,"remain,
{"learn":[0.3018748,
{"learn":[0.3071710914],"iteration":548,"passed_time":13.33701659,"remain,
{"learn":[0.3016044,
{"learn":[0.3069543703],"iteration":549,"passed_time":13.36947162,"remaini,
{"learn":[0.301457,
{"learn":[0.3066797208],"iteration":550,"passed_time":13.39140658,"remaini,
{"learn":[0.3011579,
{"learn":[0.3064156526],"iteration":551,"passed_time":13.40595289,"remaini,
{"learn":[0.3009787,
{"learn":[0.3062184358],"iteration":552,"passed_time":13.42536297,"remain,
{"learn":[0.30080243,
{"learn":[0.3059097674],"iteration":553,"passed_time":13.43993898,"remain,
{"learn":[0.30051425,
{"learn":[0.3056947447],"iteration":554,"passed_time":13.4730816,"remaini,
{"learn":[0.300297,
{"learn":[0.3056806765],"iteration":555,"passed_time":13.49679818,"remainin,
{"learn":[0.300123,
{"learn":[0.3054458022],"iteration":556,"passed_time":13.51572769,"remain,
{"learn":[0.29992906,
{"learn":[0.3053391105],"iteration":557,"passed_time":13.52775028,"remain,
{"learn":[0.29966625,
{"learn":[0.3050664759],"iteration":558,"passed_time":13.53861906,"remain,
{"learn":[0.29935061,
{"learn":[0.3048377077],"iteration":559,"passed_time":13.55911925,"remain,
{"learn":[0.2990815,
{"learn":[0.304602161],"iteration":560,"passed_time":13.5706244,"remainin,
{"learn":[0.298779,
{"learn":[0.3044450439],"iteration":561,"passed_time":13.59272067,"remainin,
{"learn":[0.298542,
{"learn":[0.3042006679],"iteration":562,"passed_time":13.60606291,"remainin,
{"learn":[0.298303,
{"learn":[0.3039640581],"iteration":563,"passed_time":13.62785001,"remaini,
{"learn":[0.2981123,
{"learn":[0.3037457854],"iteration":564,"passed_time":13.64036433,"remaini,
{"learn":[0.2979269,
{"learn":[0.3034881544],"iteration":565,"passed_time":13.65827987,"remain,
{"learn":[0.29764135,
{"learn":[0.3033445506],"iteration":566,"passed_time":13.67093063,"remain,
{"learn":[0.29745523,
{"learn":[0.3030717114],"iteration":567,"passed_time":13.68484374,"remain,
{"learn":[0.29722118,
{"learn":[0.3029493303],"iteration":568,"passed_time":13.69653012,"remain,
{"learn":[0.29696906,
{"learn":[0.3028149758],"iteration":569,"passed_time":13.70993191,"remain,
{"learn":[0.29676671,
{"learn":[0.3025578082],"iteration":570,"passed_time":13.72365053,"remain,
{"learn":[0.29669752,
{"learn":[0.3023684127],"iteration":571,"passed_time":13.73433035,"remain,
{"learn":[0.2964496,
{"learn":[0.3020985093],"iteration":572,"passed_time":13.75518756,"remaini,
{"learn":[0.2962643,
{"learn":[0.3018891051],"iteration":573,"passed_time":13.76714534,"remaini,
{"learn":[0.2962128,
{"learn":[0.3018451314],"iteration":574,"passed_time":13.78397824,"remaini,
{"learn":[0.2959790,
{"learn":[0.3015876569],"iteration":575,"passed_time":13.7969336,"remainin,
{"learn":[0.295737,
{"learn":[0.3013328583],"iteration":576,"passed_time":13.81585528,"remainin,
{"learn":[0.295663,
{"learn":[0.30099989],"iteration":577,"passed_time":13.8407646,"remaining_t,
{"learn":[0.295,
{"learn":[0.3006752075],"iteration":578,"passed_time":13.86635504,"remaining_t,
{"learn":[0.295,
{"learn":[0.3006631088],"iteration":579,"passed_time":13.88982949,"remaining_t,
{"learn":[0.294,
{"learn":[0.3004098261],"iteration":580,"passed_time":13.91171641,"remaining_t,
{"learn":[0.294,
{"learn":[0.300029983],"iteration":581,"passed_time":13.93468724,"remaining_ti,
{"learn":[0.29,
{"learn":[0.29978504],"iteration":582,"passed_time":13.96227375,"remaining_time,
{"learn":[0.,
{"learn":[0.2995267054],"iteration":583,"passed_time":13.97914767,"remaining_time,
{"learn":[0.,
{"learn":[0.2993217335],"iteration":584,"passed_time":13.99039516,"remaining_time,
{"learn":[0.,
{"learn":[0.2991562963],"iteration":585,"passed_time":14.00233016,"remaining_tim,
{"learn":[0.2,
{"learn":[0.2988642262],"iteration":586,"passed_time":14.01801291,"remaining_tim,
{"learn":[0.2,
{"learn":[0.2986567589],"iteration":587,"passed_time":14.02834115,"remaining_tim,
{"learn":[0.2,
{"learn":[0.298394059],"iteration":588,"passed_time":14.04758319,"remaining_tim,
{"learn":[0.2,
{"learn":[0.2982124002],"iteration":589,"passed_time":14.06058258,"remaining_tim,
{"learn":[0.2,
{"learn":[0.2979603992],"iteration":590,"passed_time":14.07454172,"remaining_ti,
{"learn":[0.29,
{"learn":[0.2977299427],"iteration":591,"passed_time":14.0867066,"remaining_tim,
{"learn":[0,
{"learn":[0.2974055969],"iteration":592,"passed_time":14.09966556,"remaining_time",
{"learn":[0,
{"learn":[0.2971621631],"iteration":593,"passed_time":14.11459219,"remaining_time",
{"learn":[0,
{"learn":[0.2969789628],"iteration":594,"passed_time":14.12521719,"remaining_time,
{"learn":[0.,
{"learn":[0.2966641031],"iteration":595,"passed_time":14.14513313,"remaining_ti,
{"learn":[0.29,
{"learn":[0.2964454051],"iteration":596,"passed_time":14.15692954,"remaining_ti,
{"learn":[0.29,
{"learn":[0.2962150421],"iteration":597,"passed_time":14.17062076,"remaining_ti,
{"learn":[0.29,
{"learn":[0.2959493694],"iteration":598,"passed_time":14.18346125,"remaining_t,
{"learn":[0.291,
{"learn":[0.2957367856],"iteration":599,"passed_time":14.19470365,"remaining_t,
{"learn":[0.291,
{"learn":[0.2956233246],"iteration":600,"passed_time":14.21381406,"remaining_t,
{"learn":[0.290,
{"learn":[0.2955114042],"iteration":601,"passed_time":14.22895031,"remaining_t,
{"learn":[0.290,
{"learn":[0.2952780048],"iteration":602,"passed_time":14.2564506,"remaining_t,
{"learn":[0.290,
{"learn":[0.2951720773],"iteration":603,"passed_time":14.27523429,"remaining_t,
{"learn":[0.290,
{"learn":[0.2951581374],"iteration":604,"passed_time":14.29502263,"remaining_t,
{"learn":[0.289,
{"learn":[0.2950104802],"iteration":605,"passed_time":14.31716414,"remaining_t,
{"learn":[0.289,
{"learn":[0.2948802562],"iteration":606,"passed_time":14.33668413,"remaining,
{"learn":[0.28957,
{"learn":[0.2946944451],"iteration":607,"passed_time":14.35045892,"remainin,
{"learn":[0.289451,
{"learn":[0.2945451115],"iteration":608,"passed_time":14.36200307,"remaini,
{"learn":[0.2892685,
{"learn":[0.2943945573],"iteration":609,"passed_time":14.37882268,"remaini,
{"learn":[0.2889689,
{"learn":[0.2941822961],"iteration":610,"passed_time":14.39033829,"remaini,
{"learn":[0.2887684,
{"learn":[0.2940837124],"iteration":611,"passed_time":14.40349083,"remaini,
{"learn":[0.2885142,
{"learn":[0.293851248],"iteration":612,"passed_time":14.41758144,"remainin,
{"learn":[0.288300,
{"learn":[0.2935407234],"iteration":613,"passed_time":14.43110669,"remaini,
{"learn":[0.2881281,
{"learn":[0.2933791271],"iteration":614,"passed_time":14.44497445,"remaini,
{"learn":[0.2880250,
{"learn":[0.2931346951],"iteration":615,"passed_time":14.45964608,"remaini,
{"learn":[0.2878689,
{"learn":[0.2929305385],"iteration":616,"passed_time":14.47709943,"remaini,
{"learn":[0.2876886,
{"learn":[0.2927240377],"iteration":617,"passed_time":14.48933368,"remaini,
{"learn":[0.2875192,
{"learn":[0.2924749716],"iteration":618,"passed_time":14.50290416,"remaini,
{"learn":[0.2873211,
{"learn":[0.2922898533],"iteration":619,"passed_time":14.51535831,"remaini,
{"learn":[0.287200,
{"learn":[0.2920477698],"iteration":620,"passed_time":14.53155723,"remainin,
{"learn":[0.28704,
{"learn":[0.2918202044],"iteration":621,"passed_time":14.54803059,"remaining,
{"learn":[0.28681,
{"learn":[0.2918075155],"iteration":622,"passed_time":14.55850547,"remaining,
{"learn":[0.28680,
{"learn":[0.2915032891],"iteration":623,"passed_time":14.57543619,"remainin,
{"learn":[0.28658,
{"learn":[0.2913428472],"iteration":624,"passed_time":14.58668604,"remainin,
{"learn":[0.286308,
{"learn":[0.291176811],"iteration":625,"passed_time":14.60303186,"remaining,
{"learn":[0.28609,
{"learn":[0.2910369892],"iteration":626,"passed_time":14.61553938,"remainin,
{"learn":[0.285939,
{"learn":[0.2910280615],"iteration":627,"passed_time":14.63407672,"remain,
{"learn":[0.28592745,
{"learn":[0.2908268093],"iteration":628,"passed_time":14.6451897,"remaini,
{"learn":[0.2858004,
{"learn":[0.2905289731],"iteration":629,"passed_time":14.66224031,"remain,
{"learn":[0.28554697,
{"learn":[0.290398609],"iteration":630,"passed_time":14.67485237,"remaini,
{"learn":[0.285371,
{"learn":[0.2902322895],"iteration":631,"passed_time":14.68635028,"remaini,
{"learn":[0.2852318,
{"learn":[0.290203942],"iteration":632,"passed_time":14.7023558,"remaining,
{"learn":[0.2849,
{"learn":[0.2899947152],"iteration":633,"passed_time":14.71365111,"remaining_,
{"learn":[0.2847,
{"learn":[0.2899380214],"iteration":634,"passed_time":14.73141528,"remaining_,
{"learn":[0.2846,
{"learn":[0.2899065001],"iteration":635,"passed_time":14.74313203,"remaining,
{"learn":[0.28451,
{"learn":[0.2896515229],"iteration":636,"passed_time":14.75541714,"remaining,
{"learn":[0.28434,
{"learn":[0.2894433885],"iteration":637,"passed_time":14.76790061,"remainin,
{"learn":[0.284139,
{"learn":[0.2892538062],"iteration":638,"passed_time":14.78415125,"remainin,
{"learn":[0.283988,
{"learn":[0.2889479542],"iteration":639,"passed_time":14.80057861,"remainin,
{"learn":[0.283927,
{"learn":[0.2887229226],"iteration":640,"passed_time":14.81481127,"remainin,
{"learn":[0.28367,
{"learn":[0.2885186189],"iteration":641,"passed_time":14.83653163,"remaining,
{"learn":[0.2834,
{"learn":[0.2883858092],"iteration":642,"passed_time":14.84999743,"remaining_,
{"learn":[0.2833,
{"learn":[0.2882830455],"iteration":643,"passed_time":14.8647441,"remaining_,
{"learn":[0.2830,
{"learn":[0.2880210996],"iteration":644,"passed_time":14.87528055,"remaining_,
{"learn":[0.2828,
{"learn":[0.2878411386],"iteration":645,"passed_time":14.88947584,"remainin,
{"learn":[0.282536,
{"learn":[0.2876055099],"iteration":646,"passed_time":14.90362849,"remainin,
{"learn":[0.282404,
{"learn":[0.2873628913],"iteration":647,"passed_time":14.91501281,"remainin,
{"learn":[0.282179,
{"learn":[0.2872065576],"iteration":648,"passed_time":14.93461012,"remaini,
{"learn":[0.2820199,
{"learn":[0.2870416131],"iteration":649,"passed_time":14.94685338,"remaini,
{"learn":[0.2818811,
{"learn":[0.2868412894],"iteration":650,"passed_time":14.96278941,"remaini,
{"learn":[0.2816582,
{"learn":[0.2866414861],"iteration":651,"passed_time":14.97508268,"remaini,
{"learn":[0.2814709,
{"learn":[0.2863758925],"iteration":652,"passed_time":14.99193322,"remaini,
{"learn":[0.2813146,
{"learn":[0.2861369982],"iteration":653,"passed_time":15.00481966,"remaini,
{"learn":[0.2811494,
{"learn":[0.2860261882],"iteration":654,"passed_time":15.0203033,"remainin,
{"learn":[0.281021,
{"learn":[0.2858669625],"iteration":655,"passed_time":15.03997513,"remainin,
{"learn":[0.280880,
{"learn":[0.2857214579],"iteration":656,"passed_time":15.05953129,"remainin,
{"learn":[0.280626,
{"learn":[0.2854802045],"iteration":657,"passed_time":15.07042132,"remainin,
{"learn":[0.280420,
{"learn":[0.2853579854],"iteration":658,"passed_time":15.08411111,"remaini,
{"learn":[0.2802414,
{"learn":[0.2851629885],"iteration":659,"passed_time":15.09874276,"remaini,
{"learn":[0.2801153,
{"learn":[0.2849614833],"iteration":660,"passed_time":15.10946148,"remain,
{"learn":[0.27994736,
{"learn":[0.2847561815],"iteration":661,"passed_time":15.12875674,"remain,
{"learn":[0.27993635,
{"learn":[0.2845702024],"iteration":662,"passed_time":15.14109982,"remain,
{"learn":[0.27966308,
{"learn":[0.2843819519],"iteration":663,"passed_time":15.15464018,"remain,
{"learn":[0.27956162,
{"learn":[0.2842504815],"iteration":664,"passed_time":15.1662466,"remaini,
{"learn":[0.2793378,
{"learn":[0.2840713792],"iteration":665,"passed_time":15.17990802,"remaini,
{"learn":[0.2792144,
{"learn":[0.2839096192],"iteration":666,"passed_time":15.19268812,"remain,
{"learn":[0.27905362,
{"learn":[0.2836968874],"iteration":667,"passed_time":15.20422594,"remain,
{"learn":[0.27893720,
{"learn":[0.2835825357],"iteration":668,"passed_time":15.22444617,"remai,
{"learn":[0.278780002,
{"learn":[0.2833643958],"iteration":669,"passed_time":15.23663876,"rem,
{"learn":[0.2785488779],
{"learn":[0.2830723711],"iteration":670,"passed_time":15.25909293,"rem,
{"learn":[0.278382867],,
{"learn":[0.2827879479],"iteration":671,"passed_time":15.27549743,"re,
{"learn":[0.2782023447],,
{"learn":[0.2825164553],"iteration":672,"passed_time":15.30014761,"re,
{"learn":[0.2779970725],,
{"learn":[0.2822952479],"iteration":673,"passed_time":15.35916052,"re,
{"learn":[0.2777082347],,
{"learn":[0.2821492426],"iteration":674,"passed_time":15.43622158,"re,
{"learn":[0.2775620726],,
{"learn":[0.281995367],"iteration":675,"passed_time":15.52969503,"re,
{"learn":[0.2773595891],,
{"learn":[0.2818228122],"iteration":676,"passed_time":15.59423096,"r,
{"learn":[0.2771657914],",
{"learn":[0.2816221688],"iteration":677,"passed_time":15.64057071,"r,
{"learn":[0.277049229],"i,
{"learn":[0.2814645758],"iteration":678,"passed_time":15.66382818,",
{"learn":[0.2768155133],"i,
{"learn":[0.2812450005],"iteration":679,"passed_time":15.78044096,",
{"learn":[0.2766833031],"i,
{"learn":[0.2810655271],"iteration":680,"passed_time":15.85429501,,
{"learn":[0.2765587052],"it,
{"learn":[0.2808018301],"iteration":681,"passed_time":15.86821485,,
{"learn":[0.2763980145],"it,
{"learn":[0.2806176981],"iteration":682,"passed_time":15.88254754,,
{"learn":[0.2762013575],"it,
{"learn":[0.280417841],"iteration":683,"passed_time":15.8985661,"r,
{"learn":[0.2760666242],",
{"learn":[0.2802756528],"iteration":684,"passed_time":15.91860452,"r,
{"learn":[0.276041431],"i,
{"learn":[0.2801033549],"iteration":685,"passed_time":15.93083013,",
{"learn":[0.2758722844],"i,
{"learn":[0.2799481299],"iteration":686,"passed_time":15.95532557,",
{"learn":[0.275733629],"it,
{"learn":[0.2797677916],"iteration":687,"passed_time":15.97159794,,
{"learn":[0.2755108408],"it,
{"learn":[0.2795405508],"iteration":688,"passed_time":15.98850521,,
{"learn":[0.2753253501],"it,
{"learn":[0.2793559299],"iteration":689,"passed_time":15.99907821,,
{"learn":[0.2751588558],"i,
{"learn":[0.2791773341],"iteration":690,"passed_time":16.01900083,",
{"learn":[0.2749406803],"i,
{"learn":[0.2789515599],"iteration":691,"passed_time":16.03185025,",
{"learn":[0.2748087835],"i,
{"learn":[0.278791181],"iteration":692,"passed_time":16.04526709,"r,
{"learn":[0.2745442994],",
{"learn":[0.2786509437],"iteration":693,"passed_time":16.0573465,"re,
{"learn":[0.2743199143],,
{"learn":[0.2784379981],"iteration":694,"passed_time":16.07439819,"re,
{"learn":[0.2741996532],,
{"learn":[0.2781978072],"iteration":695,"passed_time":16.08769389,"re,
{"learn":[0.2741152652],,
{"learn":[0.2780459661],"iteration":696,"passed_time":16.10165141,"r,
{"learn":[0.2739629406],",
{"learn":[0.2779218089],"iteration":697,"passed_time":16.12195626,"r,
{"learn":[0.2739174441],",
{"learn":[0.2777797103],"iteration":698,"passed_time":16.13477212,"r,
{"learn":[0.2737548799],",
{"learn":[0.2776249082],"iteration":699,"passed_time":16.15148253,",
{"learn":[0.2736047847],"i,
{"learn":[0.2774933495],"iteration":700,"passed_time":16.16198716,",
{"learn":[0.2734929425],"i,
{"learn":[0.2774769004],"iteration":701,"passed_time":16.18624662,",
{"learn":[0.2733721886],"i,
{"learn":[0.277224729],"iteration":702,"passed_time":16.19961809,"r,
{"learn":[0.2732290631],",
{"learn":[0.2769614815],"iteration":703,"passed_time":16.21777059,"r,
{"learn":[0.2730767624],",
{"learn":[0.2767373004],"iteration":704,"passed_time":16.23001112,"r,
{"learn":[0.2729139867],",
{"learn":[0.2766374458],"iteration":705,"passed_time":16.24867663,"r,
{"learn":[0.2727282031],",
{"learn":[0.2765337941],"iteration":706,"passed_time":16.26214857,"r,
{"learn":[0.2725588737],",
{"learn":[0.2763637144],"iteration":707,"passed_time":16.27515574,"r,
{"learn":[0.2724041013],",
{"learn":[0.2761540852],"iteration":708,"passed_time":16.28922764,"r,
{"learn":[0.2721895699],",
{"learn":[0.2760379012],"iteration":709,"passed_time":16.31014591,"r,
{"learn":[0.2720513858],",
{"learn":[0.2758900029],"iteration":710,"passed_time":16.32175725,"r,
{"learn":[0.2719159035],",
{"learn":[0.2757631622],"iteration":711,"passed_time":16.33531316,"r,
{"learn":[0.2717616487],",
{"learn":[0.2755063335],"iteration":712,"passed_time":16.34829381,"r,
{"learn":[0.2716642966],",
{"learn":[0.275365589],"iteration":713,"passed_time":16.35869567,"re,
{"learn":[0.2714602409],,
{"learn":[0.2752027354],"iteration":714,"passed_time":16.37261277,"r,
{"learn":[0.2712700451],",
{"learn":[0.2750776347],"iteration":715,"passed_time":16.38708031,"r,
{"learn":[0.2711141396],",
{"learn":[0.2748508378],"iteration":716,"passed_time":16.42466786,"r,
{"learn":[0.270989119],"i,
{"learn":[0.2746296805],"iteration":717,"passed_time":16.44787012,",
{"learn":[0.2708544041],"i,
{"learn":[0.2745431754],"iteration":718,"passed_time":16.4876144,",
{"learn":[0.2706604988],"i,
{"learn":[0.2743969727],"iteration":719,"passed_time":16.5511624,,
{"learn":[0.2704738447],"it,
{"learn":[0.2742451025],"iteration":720,"passed_time":16.6275939,
{"learn":[0.2702693235],"iter,
{"learn":[0.2740603517],"iteration":721,"passed_time":16.6634899,
{"learn":[0.2701362787],"iter,
{"learn":[0.2739130513],"iteration":722,"passed_time":16.6802851,
{"learn":[0.2699870561],"iter,
{"learn":[0.2737547608],"iteration":723,"passed_time":16.6919168,
{"learn":[0.269836986],"itera,
{"learn":[0.2736001731],"iteration":724,"passed_time":16.712208,
{"learn":[0.2697294137],"itera,
{"learn":[0.2734360926],"iteration":725,"passed_time":16.724440,
{"learn":[0.2695017641],"itera,
{"learn":[0.273249092],"iteration":726,"passed_time":16.7398815,
{"learn":[0.2692718867],"iter,
{"learn":[0.2730069584],"iteration":727,"passed_time":16.7518489,
{"learn":[0.2690804298],"iter,
{"learn":[0.2728180964],"iteration":728,"passed_time":16.7662585,
{"learn":[0.2688774466],"iter,
{"learn":[0.2726163878],"iteration":729,"passed_time":16.7787336,
{"learn":[0.2687558017],"iter,
{"learn":[0.272467707],"iteration":730,"passed_time":16.79189312,
{"learn":[0.2685227952],"ite,
{"learn":[0.272353948],"iteration":731,"passed_time":16.80937585,
{"learn":[0.2683446518],"it,
{"learn":[0.2722377458],"iteration":732,"passed_time":16.82189366,,
{"learn":[0.2682381058],"it,
{"learn":[0.272080424],"iteration":733,"passed_time":16.83643513,",
{"learn":[0.2680330931],"i,
{"learn":[0.2718434077],"iteration":734,"passed_time":16.85029044,,
{"learn":[0.2678513869],"it,
{"learn":[0.2716567328],"iteration":735,"passed_time":16.88573962,,
{"learn":[0.2677154968],"it,
{"learn":[0.2714767471],"iteration":736,"passed_time":16.93208742,,
{"learn":[0.2675635435],"it,
{"learn":[0.2713185907],"iteration":737,"passed_time":16.94796018,,
{"learn":[0.2674710751],"it,
{"learn":[0.271244131],"iteration":738,"passed_time":16.97168188,",
{"learn":[0.2672899756],"i,
{"learn":[0.2712369496],"iteration":739,"passed_time":16.98754274,",
{"learn":[0.267165712],"it,
{"learn":[0.2710835518],"iteration":740,"passed_time":17.00818603,,
{"learn":[0.2668511471],"it,
{"learn":[0.2708540233],"iteration":741,"passed_time":17.02044125,,
{"learn":[0.2666803391],"it,
{"learn":[0.2706201417],"iteration":742,"passed_time":17.03655164,,
{"learn":[0.2665416362],"it,
{"learn":[0.2706123185],"iteration":743,"passed_time":17.04829312,,
{"learn":[0.2663942298],"it,
{"learn":[0.2704222734],"iteration":744,"passed_time":17.06245751,,
{"learn":[0.2662526181],"it,
{"learn":[0.2702335055],"iteration":745,"passed_time":17.07477884,,
{"learn":[0.2660917622],"it,
{"learn":[0.2700955117],"iteration":746,"passed_time":17.08759975,,
{"learn":[0.2659058534],"it,
{"learn":[0.2699523853],"iteration":747,"passed_time":17.11111827,,
{"learn":[0.2657074121],"it,
{"learn":[0.2697363175],"iteration":748,"passed_time":17.13407307,,
{"learn":[0.265599661],"ite,
{"learn":[0.2695943104],"iteration":749,"passed_time":17.14756804,
{"learn":[0.2654411315],"ite,
{"learn":[0.269391776],"iteration":750,"passed_time":17.17473722,,
{"learn":[0.2652891506],"it,
{"learn":[0.269237355],"iteration":751,"passed_time":17.2175465,",
{"learn":[0.2651829533],"i,
{"learn":[0.2692217568],"iteration":752,"passed_time":17.24670893,",
{"learn":[0.2650068937],"i,
{"learn":[0.269090367],"iteration":753,"passed_time":17.29015367,"r,
{"learn":[0.264844529],"i,
{"learn":[0.2689136575],"iteration":754,"passed_time":17.31372211,",
{"learn":[0.2646652852],"i,
{"learn":[0.2689069935],"iteration":755,"passed_time":17.35000387,,
{"learn":[0.264481607],"ite,
{"learn":[0.2688096211],"iteration":756,"passed_time":17.36744012,
{"learn":[0.2643104248],"ite,
{"learn":[0.2687353281],"iteration":757,"passed_time":17.38998288,
{"learn":[0.2641338963],"ite,
{"learn":[0.2684939187],"iteration":758,"passed_time":17.40286701,
{"learn":[0.2640347674],"ite,
{"learn":[0.2683701795],"iteration":759,"passed_time":17.41790569,
{"learn":[0.2639092649],"it,
{"learn":[0.268221946],"iteration":760,"passed_time":17.43052813,",
{"learn":[0.2637169731],"i,
{"learn":[0.2680361966],"iteration":761,"passed_time":17.44497484,",
{"learn":[0.2635756727],"i,
{"learn":[0.267813937],"iteration":762,"passed_time":17.45741616,"r,
{"learn":[0.2633977541],",
{"learn":[0.2675813385],"iteration":763,"passed_time":17.47021636,"r,
{"learn":[0.263242385],"i,
{"learn":[0.2674756615],"iteration":764,"passed_time":17.48946398,",
{"learn":[0.2630517581],"i,
{"learn":[0.2673036756],"iteration":765,"passed_time":17.50420501,",
{"learn":[0.26290757],"ite,
{"learn":[0.2671872165],"iteration":766,"passed_time":17.52099322,
{"learn":[0.2627319477],"ite,
{"learn":[0.2670551767],"iteration":767,"passed_time":17.53277241,
{"learn":[0.2625916832],"ite,
{"learn":[0.2669216432],"iteration":768,"passed_time":17.56006668,
{"learn":[0.2624121557],"ite,
{"learn":[0.2668081744],"iteration":769,"passed_time":17.58705211,
{"learn":[0.2622708888],"ite,
{"learn":[0.2666210676],"iteration":770,"passed_time":17.60212058,
{"learn":[0.2621198394],"ite,
{"learn":[0.2665518401],"iteration":771,"passed_time":17.62134111,
{"learn":[0.2619855001],"ite,
{"learn":[0.2664446049],"iteration":772,"passed_time":17.63424652,
{"learn":[0.2618435018],"it,
{"learn":[0.2663128662],"iteration":773,"passed_time":17.64978079,,
{"learn":[0.2616053375],"it,
{"learn":[0.2660875996],"iteration":774,"passed_time":17.66261658,,
{"learn":[0.2613980383],"it,
{"learn":[0.2659241953],"iteration":775,"passed_time":17.68302347,,
{"learn":[0.2612905682],"it,
{"learn":[0.2657843397],"iteration":776,"passed_time":17.69469639,,
{"learn":[0.2612096593],"it,
{"learn":[0.2657044244],"iteration":777,"passed_time":17.70810325,
{"learn":[0.2610440839],"ite,
{"learn":[0.2656986876],"iteration":778,"passed_time":17.7222908,
{"learn":[0.260868968],"itera,
{"learn":[0.2655677826],"iteration":779,"passed_time":17.734433,
{"learn":[0.2607422215],"itera,
{"learn":[0.265389943],"iteration":780,"passed_time":17.7481354,
{"learn":[0.2606465597],"ite,
{"learn":[0.2652498907],"iteration":781,"passed_time":17.76263208,
{"learn":[0.2606337353],"ite,
{"learn":[0.2651788541],"iteration":782,"passed_time":17.7825295,
{"learn":[0.2605468609],"iter,
{"learn":[0.2649363705],"iteration":783,"passed_time":17.8105973,
{"learn":[0.2603520329],"iter,
{"learn":[0.2648108207],"iteration":784,"passed_time":17.853891,
{"learn":[0.2602991244],"itera,
{"learn":[0.2646099233],"iteration":785,"passed_time":17.872140,
{"learn":[0.2600611549],"itera,
{"learn":[0.2644520233],"iteration":786,"passed_time":17.936862,
{"learn":[0.2598360723],"itera,
{"learn":[0.2644456001],"iteration":787,"passed_time":17.95217,
{"learn":[0.2597677706],"itera,
{"learn":[0.2642302993],"iteration":788,"passed_time":17.966848,
{"learn":[0.2596019493],"itera,
{"learn":[0.264108282],"iteration":789,"passed_time":17.9855929,
{"learn":[0.259365276],"itera,
{"learn":[0.2638738959],"iteration":790,"passed_time":18.0047,
{"learn":[0.2592275758],"iterati,
{"learn":[0.2637330845],"iteration":791,"passed_time":18.025,
{"learn":[0.2590431251],"iteratio,
{"learn":[0.263641558],"iteration":792,"passed_time":18.0590,
{"learn":[0.258780583],"iteratio,
{"learn":[0.2634711201],"iteration":793,"passed_time":18.082,
{"learn":[0.2586058402],"iteratio,
{"learn":[0.2633493817],"iteration":794,"passed_time":18.098,
{"learn":[0.2584934145],"iterati,
{"learn":[0.2632299185],"iteration":795,"passed_time":18.113,
{"learn":[0.2583426638],"iteratio,
{"learn":[0.2630391458],"iteration":796,"passed_time":18.124,
{"learn":[0.2581197826],"iteratio,
{"learn":[0.2628458277],"iteration":797,"passed_time":18.14,
{"learn":[0.2580115945],"iteratio,
{"learn":[0.2626688265],"iteration":798,"passed_time":18.162,
{"learn":[0.2578142786],"iteratio,
{"learn":[0.2624597508],"iteration":799,"passed_time":18.184,
{"learn":[0.257575452],"iteratio,
{"learn":[0.2622913255],"iteration":800,"passed_time":18.195,
{"learn":[0.2574658528],"iteratio,
{"learn":[0.2621958937],"iteration":801,"passed_time":18.210,
{"learn":[0.2573577637],"iteratio,
{"learn":[0.2620276628],"iteration":802,"passed_time":18.22,
{"learn":[0.257190951],"iteration",
{"learn":[0.2618963607],"iteration":803,"passed_time":18.2,
{"learn":[0.2569868418],"iteration",
{"learn":[0.2617599617],"iteration":804,"passed_time":18.2,
{"learn":[0.2568839484],"iteration",
{"learn":[0.2615243065],"iteration":805,"passed_time":18.2,
{"learn":[0.2567284321],"iteration",
{"learn":[0.2613858826],"iteration":806,"passed_time":18.2,
{"learn":[0.2565903932],"iteration",
{"learn":[0.2612975113],"iteration":807,"passed_time":18.3,
{"learn":[0.2564336506],"iteration,
{"learn":[0.2611386907],"iteration":808,"passed_time":18.31,
{"learn":[0.2562207236],"iteration,
{"learn":[0.2609866695],"iteration":809,"passed_time":18.32,
{"learn":[0.2560913584],"iteratio,
{"learn":[0.2608018121],"iteration":810,"passed_time":18.341,
{"learn":[0.2559745894],"iteratio,
{"learn":[0.2606395396],"iteration":811,"passed_time":18.35,
{"learn":[0.2558058223],"iteration,
{"learn":[0.2605443972],"iteration":812,"passed_time":18.37,
{"learn":[0.255678073],"iteration",
{"learn":[0.2604432549],"iteration":813,"passed_time":18.3,
{"learn":[0.2556036344],"iteration",
{"learn":[0.2602979352],"iteration":814,"passed_time":18.4,
{"learn":[0.255410548],"iteration",
{"learn":[0.2601816701],"iteration":815,"passed_time":18.4,
{"learn":[0.2552539537],"iteration",
{"learn":[0.2600973281],"iteration":816,"passed_time":18.4,
{"learn":[0.2550508513],"iteration",
{"learn":[0.2599316187],"iteration":817,"passed_time":18.4,
{"learn":[0.254848946],"iteration":,
{"learn":[0.2597799871],"iteration":818,"passed_time":18,
{"learn":[0.2546205988],"iteration":,
{"learn":[0.2596568381],"iteration":819,"passed_time":18.,
{"learn":[0.2544596557],"iteration":,
{"learn":[0.2595575707],"iteration":820,"passed_time":18.,
{"learn":[0.2544486557],"iteration":,
{"learn":[0.2593864988],"iteration":821,"passed_time":18.,
{"learn":[0.2543410913],"iteration":,
{"learn":[0.2592880305],"iteration":822,"passed_time":18.,
{"learn":[0.2542409137],"iteration":,
{"learn":[0.2591531902],"iteration":823,"passed_time":18.,
{"learn":[0.2541036787],"iteration":,
{"learn":[0.2589842413],"iteration":824,"passed_time":18.,
{"learn":[0.2539290229],"iteration":,
{"learn":[0.2588353201],"iteration":825,"passed_time":18,
{"learn":[0.2537767147],"iteration":8,
{"learn":[0.2586644621],"iteration":826,"passed_time":18,
{"learn":[0.2535735039],"iteration":8,
{"learn":[0.2584643389],"iteration":827,"passed_time":18,
{"learn":[0.2534300169],"iteration":8,
{"learn":[0.2583209517],"iteration":828,"passed_time":18,
{"learn":[0.2533062767],"iteration":8,
{"learn":[0.2581784976],"iteration":829,"passed_time":18,
{"learn":[0.2531564959],"iteration":8,
{"learn":[0.2580853397],"iteration":830,"passed_time":18,
{"learn":[0.2529908715],"iteration":8,
{"learn":[0.2579880511],"iteration":831,"passed_time":,
{"learn":[0.252880566],"iteration":832,,
{"learn":[0.2577721928],"iteration":832,"passed_time",
{"learn":[0.2528690159],"iteration":833,,
{"learn":[0.2575425054],"iteration":833,"passed_time",
{"learn":[0.2527291879],"iteration":834,,
{"learn":[0.2573946986],"iteration":834,"passed_time",
{"learn":[0.2525705673],"iteration":835,,
{"learn":[0.257223148],"iteration":835,"passed_time":,
{"learn":[0.2524592667],"iteration":83,
{"learn":[0.2571154753],"iteration":836,"passed_time":1,
{"learn":[0.2523099863],"iteration":8,
{"learn":[0.2568911096],"iteration":837,"passed_time":1,
{"learn":[0.2521652765],"iteration":83,
{"learn":[0.2566911106],"iteration":838,"passed_time":1,
{"learn":[0.2519884375],"iteration":83,
{"learn":[0.2564916289],"iteration":839,"passed_time":1,
{"learn":[0.2518377737],"iteration":84,
{"learn":[0.2563768708],"iteration":840,"passed_time":1,
{"learn":[0.2516763467],"iteration":8,
{"learn":[0.2562404225],"iteration":841,"passed_time":18,
{"learn":[0.251490243],"iteration":84,
{"learn":[0.256018743],"iteration":842,"passed_time":18,
{"learn":[0.2512761405],"iteration":8,
{"learn":[0.2559001065],"iteration":843,"passed_time":18,
{"learn":[0.2511430245],"iteration":8,
{"learn":[0.2557852487],"iteration":844,"passed_time":18,
{"learn":[0.2510158172],"iteration":8,
{"learn":[0.2555966468],"iteration":845,"passed_time":18,
{"learn":[0.250838375],"iteration":84,
{"learn":[0.255492217],"iteration":846,"passed_time":18,
{"learn":[0.2506763213],"iteration":,
{"learn":[0.2553060647],"iteration":847,"passed_time":18.,
{"learn":[0.250418099],"iteration":,
{"learn":[0.2552085143],"iteration":848,"passed_time":18.,
{"learn":[0.2502520065],"iteration":,
{"learn":[0.2549957363],"iteration":849,"passed_time":19.,
{"learn":[0.2501298627],"iteration",
{"learn":[0.2548102549],"iteration":850,"passed_time":19.0,
{"learn":[0.2501187083],"iteration",
{"learn":[0.2546898624],"iteration":851,"passed_time":19.0,
{"learn":[0.2501099245],"iteration,
{"learn":[0.2545465465],"iteration":852,"passed_time":19.05,
{"learn":[0.2499192217],"iteration,
{"learn":[0.2543664858],"iteration":853,"passed_time":19.07,
{"learn":[0.2497899565],"iteration,
{"learn":[0.2541834421],"iteration":854,"passed_time":19.08,
{"learn":[0.2496493906],"iteratio,
{"learn":[0.2540996732],"iteration":855,"passed_time":19.097,
{"learn":[0.2495131979],"iteratio,
{"learn":[0.2540948402],"iteration":856,"passed_time":19.109,
{"learn":[0.2493919839],"iterati,
{"learn":[0.2538872452],"iteration":857,"passed_time":19.1224,
{"learn":[0.2492828668],"iterati,
{"learn":[0.253724372],"iteration":858,"passed_time":19.14042,
{"learn":[0.2491614868],"iterat,
{"learn":[0.2535784546],"iteration":859,"passed_time":19.15802,
{"learn":[0.2489881816],"iterat,
{"learn":[0.253399666],"iteration":860,"passed_time":19.175559,
{"learn":[0.2488856681],"itera,
{"learn":[0.2532555509],"iteration":861,"passed_time":19.19436,
{"learn":[0.2487545457],"iterat,
{"learn":[0.2530406464],"iteration":862,"passed_time":19.2152,
{"learn":[0.2485905979],"iterati,
{"learn":[0.2528701395],"iteration":863,"passed_time":19.2299,
{"learn":[0.2484560696],"iterati,
{"learn":[0.2527178386],"iteration":864,"passed_time":19.2409,
{"learn":[0.2482524069],"iterati,
{"learn":[0.2525586565],"iteration":865,"passed_time":19.261,
{"learn":[0.2481333217],"iterati,
{"learn":[0.2523601959],"iteration":866,"passed_time":19.2745,
{"learn":[0.2480386269],"iterati,
{"learn":[0.2522280106],"iteration":867,"passed_time":19.2886,
{"learn":[0.2479066942],"iterati,
{"learn":[0.2520453028],"iteration":868,"passed_time":19.3008,
{"learn":[0.2478035963],"iterati,
{"learn":[0.2518868871],"iteration":869,"passed_time":19.314,
{"learn":[0.247671936],"iteration,
{"learn":[0.2517604996],"iteration":870,"passed_time":19.32,
{"learn":[0.2474995102],"iteration,
{"learn":[0.2516271393],"iteration":871,"passed_time":19.33,
{"learn":[0.2474758478],"iteration,
{"learn":[0.2515166388],"iteration":872,"passed_time":19.3,
{"learn":[0.247329801],"iteration":,
{"learn":[0.2514326394],"iteration":873,"passed_time":19.,
{"learn":[0.2471841227],"iteration":,
{"learn":[0.2512926392],"iteration":874,"passed_time":19,
{"learn":[0.2470134862],"iteration":8,
{"learn":[0.2511328392],"iteration":875,"passed_time":19,
{"learn":[0.2468925374],"iteration":,
{"learn":[0.2509595566],"iteration":876,"passed_time":19.,
{"learn":[0.2467568512],"iteration,
{"learn":[0.2508513054],"iteration":877,"passed_time":19.43,
{"learn":[0.2466108924],"iteratio,
{"learn":[0.2506971308],"iteration":878,"passed_time":19.452,
{"learn":[0.2464368057],"iterati,
{"learn":[0.2506195855],"iteration":879,"passed_time":19.4672,
{"learn":[0.2463212754],"iterati,
{"learn":[0.2504528899],"iteration":880,"passed_time":19.48,
{"learn":[0.2461538804],"iteration,
{"learn":[0.2503004674],"iteration":881,"passed_time":19.49,
{"learn":[0.2460071584],"iteration,
{"learn":[0.2501529775],"iteration":882,"passed_time":19.51,
{"learn":[0.2460006486],"iteration,
{"learn":[0.2500411966],"iteration":883,"passed_time":19.5,
{"learn":[0.2458040461],"iteration",
{"learn":[0.2498680319],"iteration":884,"passed_time":19.5,
{"learn":[0.2455702365],"iteration",
{"learn":[0.2497561097],"iteration":885,"passed_time":19.5,
{"learn":[0.245461051],"iteration":,
{"learn":[0.2496270598],"iteration":886,"passed_time":19.,
{"learn":[0.2452320321],"iteration":,
{"learn":[0.2494885745],"iteration":887,"passed_time":19.,
{"learn":[0.2451302056],"iteration",
{"learn":[0.2493382995],"iteration":888,"passed_time":19.5,
{"learn":[0.2449575419],"iteration,
{"learn":[0.2492313337],"iteration":889,"passed_time":19.60,
{"learn":[0.244827691],"iteration",
{"learn":[0.2491344645],"iteration":890,"passed_time":19.,
{"learn":[0.244631505],"iteration":8,
{"learn":[0.2490431893],"iteration":891,"passed_time":1,
{"learn":[0.244447657],"iteration":892,
{"learn":[0.2489552532],"iteration":892,"passed_time":,
{"learn":[0.2443021465],"iteration":893,
{"learn":[0.2489510665],"iteration":893,"passed_time":,
{"learn":[0.2441440357],"iteration":894,
{"learn":[0.2487607167],"iteration":894,"passed_time":,
{"learn":[0.2440279701],"iteration":89,
{"learn":[0.2486688203],"iteration":895,"passed_time":1,
{"learn":[0.2439135085],"iteration":89,
{"learn":[0.2485563884],"iteration":896,"passed_time":1,
{"learn":[0.2439069109],"iteration":89,
{"learn":[0.2484342684],"iteration":897,"passed_time":1,
{"learn":[0.2437958837],"iteration":89,
{"learn":[0.2482994732],"iteration":898,"passed_time":1,
{"learn":[0.2436579427],"iteration":,
{"learn":[0.2481948066],"iteration":899,"passed_time":19.,
{"learn":[0.2435779647],"iteration":,
{"learn":[0.2480822659],"iteration":900,"passed_time":19.,
{"learn":[0.2434544399],"iteration",
{"learn":[0.2479140865],"iteration":901,"passed_time":19.7,
{"learn":[0.2433603586],"iteration",
{"learn":[0.2478015822],"iteration":902,"passed_time":19.,
{"learn":[0.2432427804],"iteration":,
{"learn":[0.2476737017],"iteration":903,"passed_time":19,
{"learn":[0.2431204118],"iteration":9,
{"learn":[0.2475945997],"iteration":904,"passed_time":19,
{"learn":[0.2430291011],"iteration":,
{"learn":[0.2474729771],"iteration":905,"passed_time":19.,
{"learn":[0.242911881],"iteration":9,
{"learn":[0.24739566],"iteration":906,"passed_time":19.8,
{"learn":[0.2427690514],"iteration,
{"learn":[0.2472258527],"iteration":907,"passed_time":19.88,
{"learn":[0.2426927187],"iteration,
{"learn":[0.2470354182],"iteration":908,"passed_time":19.90,
{"learn":[0.2425401687],"iteration,
{"learn":[0.246771417],"iteration":909,"passed_time":19.919,
{"learn":[0.2424124238],"iteratio,
{"learn":[0.2466575868],"iteration":910,"passed_time":19.940,
{"learn":[0.242229377],"iteration,
{"learn":[0.2465779141],"iteration":911,"passed_time":19.95,
{"learn":[0.2421516318],"iteration,
{"learn":[0.2463254175],"iteration":912,"passed_time":19.9,
{"learn":[0.2420395913],"iteration",
{"learn":[0.2462359751],"iteration":913,"passed_time":19.9,
{"learn":[0.2418010836],"iteration,
{"learn":[0.2461429117],"iteration":914,"passed_time":19.99,
{"learn":[0.2416766765],"iteration,
{"learn":[0.2459337697],"iteration":915,"passed_time":20.0,
{"learn":[0.241452377],"iteration":,
{"learn":[0.2458799548],"iteration":916,"passed_time":20.,
{"learn":[0.2413218424],"iteration":,
{"learn":[0.2457326],"iteration":917,"passed_time":20.036,
{"learn":[0.2411621976],"iteratio,
{"learn":[0.2456288735],"iteration":918,"passed_time":20.047,
{"learn":[0.2409945184],"iterati,
{"learn":[0.2454593467],"iteration":919,"passed_time":20.0613,
{"learn":[0.2408748481],"iterati,
{"learn":[0.2453870785],"iteration":920,"passed_time":20.0797,
{"learn":[0.2408374815],"iterati,
{"learn":[0.2453080828],"iteration":921,"passed_time":20.0,
{"learn":[0.2407197156],"iteration,
{"learn":[0.2451453429],"iteration":922,"passed_time":20.10,
{"learn":[0.240587207],"iteration,
{"learn":[0.2450431853],"iteration":923,"passed_time":20.12,
{"learn":[0.2404589274],"iteration,
{"learn":[0.2449083978],"iteration":924,"passed_time":20.14,
{"learn":[0.2403028361],"iteratio,
{"learn":[0.2447887683],"iteration":925,"passed_time":20.15,
{"learn":[0.2402349246],"iteration,
{"learn":[0.2446921855],"iteration":926,"passed_time":20.16,
{"learn":[0.2400825328],"iteration,
{"learn":[0.2445210866],"iteration":927,"passed_time":20.17,
{"learn":[0.2399335207],"iteration,
{"learn":[0.2442811976],"iteration":928,"passed_time":20.19,
{"learn":[0.2397980404],"iteration,
{"learn":[0.2441726793],"iteration":929,"passed_time":20.20,
{"learn":[0.2396512607],"iteratio,
{"learn":[0.2440333869],"iteration":930,"passed_time":20.21,
{"learn":[0.2395350485],"iteratio,
{"learn":[0.2438761254],"iteration":931,"passed_time":20.238,
{"learn":[0.2393790245],"iteratio,
{"learn":[0.2437536391],"iteration":932,"passed_time":20.249,
{"learn":[0.2391649002],"iterat,
{"learn":[0.2436742944],"iteration":933,"passed_time":20.2659,
{"learn":[0.2390291409],"iterati,
{"learn":[0.243610475],"iteration":934,"passed_time":20.27666,
{"learn":[0.2389431219],"itera,
{"learn":[0.2434832295],"iteration":935,"passed_time":20.289883,
{"learn":[0.2388007731],"itera,
{"learn":[0.2433377317],"iteration":936,"passed_time":20.31369,
{"learn":[0.2386689796],"iterat,
{"learn":[0.2432274633],"iteration":937,"passed_time":20.33172,
{"learn":[0.2385063658],"iterat,
{"learn":[0.2430918187],"iteration":938,"passed_time":20.34900,
{"learn":[0.2383794485],"iterat,
{"learn":[0.2429609477],"iteration":939,"passed_time":20.37100,
{"learn":[0.2382532091],"iterat,
{"learn":[0.242807666],"iteration":940,"passed_time":20.38928,
{"learn":[0.2381054351],"iterat,
{"learn":[0.2426556038],"iteration":941,"passed_time":20.4087,
{"learn":[0.2379613631],"iterati,
{"learn":[0.2425647459],"iteration":942,"passed_time":20.4378,
{"learn":[0.2378061353],"iterati,
{"learn":[0.2424353764],"iteration":943,"passed_time":20.454,
{"learn":[0.2377934687],"iteratio,
{"learn":[0.2422759062],"iteration":944,"passed_time":20.472,
{"learn":[0.2375629108],"iteratio,
{"learn":[0.2421440058],"iteration":945,"passed_time":20.496,
{"learn":[0.2374671418],"iteratio,
{"learn":[0.2420267683],"iteration":946,"passed_time":20.534,
{"learn":[0.2373693247],"iteratio,
{"learn":[0.2419256053],"iteration":947,"passed_time":20.568,
{"learn":[0.2372247376],"iteratio,
{"learn":[0.2417652488],"iteration":948,"passed_time":20.593,
{"learn":[0.2370611198],"iteratio,
{"learn":[0.2415975019],"iteration":949,"passed_time":20.618,
{"learn":[0.2369173524],"iterati,
{"learn":[0.2414782724],"iteration":950,"passed_time":20.6410,
{"learn":[0.2367977713],"iterati,
{"learn":[0.2413214749],"iteration":951,"passed_time":20.66,
{"learn":[0.2366453944],"iteration,
{"learn":[0.241154854],"iteration":952,"passed_time":20.678,
{"learn":[0.236513318],"iteration,
{"learn":[0.241028383],"iteration":953,"passed_time":20.6977,
{"learn":[0.2364090855],"iteratio,
{"learn":[0.2409134566],"iteration":954,"passed_time":20.7096,
{"learn":[0.2362317113],"iteratio,
{"learn":[0.2408260944],"iteration":955,"passed_time":20.7289,
{"learn":[0.2361610161],"iteratio,
{"learn":[0.2406874977],"iteration":956,"passed_time":20.7426,
{"learn":[0.2360457904],"iteratio,
{"learn":[0.2405127859],"iteration":957,"passed_time":20.7617,
{"learn":[0.2358852552],"iteration":958,"passed_time":20.77537212,"remaining_time":0.8882067329},
{"learn":[0.2358275845],"iteration":959,"passed_time":20.79111238,"remaining_time":0.8662963492},
{"learn":[0.2356808275],"iteration":960,"passed_time":20.80766149,"remaining_time":0.8444316316},
{"learn":[0.2354905576],"iteration":961,"passed_time":20.83918305,"remaining_time":0.8231693929},
{"learn":[0.2354207847],"iteration":962,"passed_time":20.86137092,"remaining_time":0.8015272318},
{"learn":[0.2352792383],"iteration":963,"passed_time":20.88073376,"remaining_time":0.7797784392},
{"learn":[0.2351270753],"iteration":964,"passed_time":20.90849297,"remaining_time":0.7583391233},
{"learn":[0.2350642659],"iteration":965,"passed_time":20.95038184,"remaining_time":0.7373840399},
{"learn":[0.2349578159],"iteration":966,"passed_time":20.97763157,"remaining_time":0.7158860825},
{"learn":[0.2348363669],"iteration":967,"passed_time":21.00537255,"remaining_time":0.6943924809},
{"learn":[0.2346786471],"iteration":968,"passed_time":21.03094428,"remaining_time":0.6728165868},
{"learn":[0.2345565396],"iteration":969,"passed_time":21.04620595,"remaining_time":0.6509135862},
{"learn":[0.234460167],"iteration":970,"passed_time":21.06101364,"remaining_time":0.6290107061},
{"learn":[0.2343528965],"iteration":971,"passed_time":21.07272714,"remaining_time":0.6070332921},
{"learn":[0.2342495414],"iteration":972,"passed_time":21.09687351,"remaining_time":0.5854219782},
{"learn":[0.2341180783],"iteration":973,"passed_time":21.10793949,"remaining_time":0.5634562904},
{"learn":[0.2340156249],"iteration":974,"passed_time":21.12747876,"remaining_time":0.5417302247},
{"learn":[0.2338543718],"iteration":975,"passed_time":21.14173952,"remaining_time":0.5198788406},
{"learn":[0.2337197856],"iteration":976,"passed_time":21.15814849,"remaining_time":0.4980935674},
{"learn":[0.2335977689],"iteration":977,"passed_time":21.16942442,"remaining_time":0.4762038213},
{"learn":[0.2334840559],"iteration":978,"passed_time":21.18587307,"remaining_time":0.4544467154},
{"learn":[0.2333789666],"iteration":979,"passed_time":21.19996357,"remaining_time":0.4326523178},
{"learn":[0.2332655521],"iteration":980,"passed_time":21.21159256,"remaining_time":0.4108259516},
{"learn":[0.2331913845],"iteration":981,"passed_time":21.23073146,"remaining_time":0.3891580105},
{"learn":[0.2330508673],"iteration":982,"passed_time":21.24337181,"remaining_time":0.3673828288},
{"learn":[0.2328667469],"it,
{"learn":[0.2365883342],"iteration":983,"passed_time":21.25298129,",
{"learn":[0.2327166841],"it,
{"learn":[0.2364778931],"iteration":984,"passed_time":21.26575713,",
{"learn":[0.232609198],"ite,
{"learn":[0.2363608388],"iteration":985,"passed_time":21.28466099,,
{"learn":[0.2324832524],"ite,
{"learn":[0.2361851971],"iteration":986,"passed_time":21.29943668,
{"learn":[0.2323078486],"iter,
{"learn":[0.2360155384],"iteration":987,"passed_time":21.32058943,
{"learn":[0.2321796006],"iter,
{"learn":[0.2359470035],"iteration":988,"passed_time":21.33322301,
{"learn":[0.2320484017],"iteration":989,"passed_time":21.3544112,"remaining_time":0.2157011233},
{"learn":[0.2319480298],"iteration":990,"passed_time":21.36552712,"remaining_time":0.1940360687},
{"learn":[0.2318173567],"iteration":991,"passed_time":21.37813601,"remaining_time":0.1724043226},
{"learn":[0.231714318],"iteration":992,"passed_time":21.39383407,"remaining_time":0.1508125262},
{"learn":[0.231582358],"iteration":993,"passed_time":21.40454983,"remaining_time":0.1292025141},
{"learn":[0.2314845862],"iterati,
{"learn":[0.2350792054],"iteration":994,"passed_time":21.41854,
{"learn":[0.2313663109],"iteration":995,"passed_time":21.43726291,"remaining_time":0.08609342534},
{"learn":[0.2312935416],"iteration":996,"passed_time":21.45426604,"remaining_time":0.06455646752},
{"learn":[0.2311935603],"iterati,
{"learn":[0.2347131567],"iteration":997,"passed_time":21.459991,
{"learn":[0.2310370882],"iterati,
{"learn":[0.2345617309],"iteration":998,"passed_time":21.478321,
{"learn":[0.2308908846],"iterati,
{"learn":[0.2344474421],"iteration":999,"passed_time":21.49128008,"remaining_time":0}
]}